{
    "created_time": "2018-06-15T13:43:29+0000",
    "message": "哈囉，大家好，今年開放政府夥伴會議 OGP Summit 將於 7\/17 ~ 7\/19 於喬治亞 Georgia Tbilisi 舉辦，由於喬治亞共和國長期不發台灣人簽證，因此今年 開放文化基金會 OCF 在年初募款跟出國參訪計畫上皆沒有辦法預先策劃。但經過 OCF 及透過一些友好國際組織持續向主辦單位反應，上週突然收到消息，因為舉辦 OGP Summit 的關係，只要在 6\/25 之前註冊大會，包括台灣人也可以得到免簽。\n\n但時間緊急，有興趣參加，也想和與開放文化基金會和 g0v 夥伴組團的朋友，請參考這份文件並與我們聯繫：",
    "story": "Wu Min Hsuan shared a link to the group: g0v.tw 後勤中心.",
    "id": "2002582599755897_1685482674861465",
    "link": "https:\/\/hackmd.io\/SaSE5PveSkO3mdUad25igQ",
    "name": "[緊急] 隨團參與 OGP Summit 2018 - HackMD",
    "picture": "https:\/\/external.xx.fbcdn.net\/safe_image.php?w=130&h=130&url=https%3A%2F%2Fhackmd.io%2Ffavicon.png&cfs=1&_nc_hash=AQAzqzntUZcSquU9",
    "updated_time": "2018-06-15T15:12:06+0000",
    "caption": "hackmd.io",
    "shares": {
        "count": 2
    },
    "likes": {
        "summary": {
            "total_count": 31
        }
    },
    "comments": {
        "data": [
            {
                "created_time": "2018-06-15T15:12:04+0000",
                "message": "哇哦，是那個世界上少數連簽證都不發的喬治亞（驚）",
                "id": "1685578351518564"
            }
        ],
        "summary": {
            "total_count": 1
        }
    }
}