{
    "created_time": "2014-07-10T17:44:17+0000",
    "message": "簡單的說就是要做一個網站放入所有候選人的資訊，我在著手做一些程式的雛型，但現在遇到幾個問題，希望能夠有人協助。\n\n年底的九合一選舉，有下面幾個選舉類型選舉區資訊比較混亂：\n# 鄉鎮市民代表\n# 直轄市議員\n# 直轄市山地原住民區民代表\n# 縣市議員\n\n例如直轄市山地原住民區民代表新北市公告像這樣\n\n新北市烏來區民代表會\n                     * (一)第1選舉區：忠治里。\n                      (二)第2選舉區：烏來里、孝義里。\n                      (三)第3選舉區：信賢里。\n                      (四)第4選舉區：福山里。\n\n希望有人能夠協助整理成這樣\n\n直轄市山地原住民區民代表|新北市|烏來區\n第1選舉區|忠治里\n第2選舉區|烏來里,孝義里\n第3選舉區|信賢里\n第4選舉區|福山里\n\n接著我就可以透過程式直接整批匯入系統\n\n我會先處理程式的開發工作，如果有人能夠幫忙整理資料，應該可以比較快讓網站上線",
    "story": "Finjon Kiang shared a link to the group: g0v.tw 後勤中心.",
    "id": "387816094628136_649811895095220",
    "link": "https:\/\/g0v.hackpad.com\/SP93kHqeeFM",
    "description": "發起人\/拋磚人：Ringo Lee + edgar （from googlegroups) *狀態： 概念發想 *專案簡介： *台灣人總是在選藍綠，只顧把票投給支持的顏色政黨，卻不去考慮所選的人是不是能對社會有貢獻、做對的事。這個專頁也可以教育民眾不要只是讓候選人出來拜託拜託、在市場握手、用選舉車大街小巷廣播擾民，就應該把票投給他們。 *不再只是依靠候選人在議會的出席率、提案數等來評斷候選人，而是直接就其選舉提出的政見達成率來打成績，且是由選區選民直接監督對候選人有選票的壓力。也不會被出席率、提案數所誤導。 *最終，提高民眾平日就要有監督的意識，而不是選完後等下一次選舉再說。 *工作目標：",
    "name": "候選人政見專頁",
    "picture": "https:\/\/external.xx.fbcdn.net\/safe_image.php?d=AQC59obiu8SVwA-t&w=130&h=130&url=https%3A%2F%2Fg0v.hackpad.com%2Fstatic%2Fimg%2Fpencil-love.png&cfs=1&_nc_hash=AQCd4tb6KYrhZXMZ",
    "updated_time": "2014-07-17T05:32:30+0000",
    "caption": "g0v.hackpad.com",
    "from": {
        "name": "Finjon Kiang",
        "id": "10211662005529746"
    },
    "likes": {
        "summary": {
            "total_count": 25
        }
    },
    "comments": {
        "data": [
            {
                "created_time": "2014-07-11T00:52:12+0000",
                "from": {
                    "name": "艾德格",
                    "id": "10155541409188090"
                },
                "message": "有人跳坑了，但坑又變大了～XD",
                "id": "649946765081733"
            },
            {
                "created_time": "2014-07-11T13:51:11+0000",
                "from": {
                    "name": "Finjon Kiang",
                    "id": "10211662005529746"
                },
                "message": "有空的人可以幫忙踹踹這個雛型： http:\/\/k.olc.tw\/elections\/ ;)",
                "id": "650353071707769"
            },
            {
                "created_time": "2014-07-17T05:32:30+0000",
                "from": {
                    "name": "Finjon Kiang",
                    "id": "10211662005529746"
                },
                "message": "有網友提到想要協助，我進一步開了這個做整理，歡迎一起參與： https:\/\/g0v.hackpad.com\/2014-XZIY7ahNhtC",
                "id": "652813671461709"
            }
        ],
        "summary": {
            "total_count": 3
        }
    }
}