{
    "created_time": "2014-05-07T15:36:54+0000",
    "message": "現在所有公部門的資訊服務外包，通通都有一個很嚴重、卻又沒有人去注意的問題。那就是資訊服務外包，其作業流程以及原始程式碼，其所有權應該歸公部門所有，而非屬於私人公司的專利。例如像戶政系統，其作業流程以及原始程式碼，其所有權應歸戶政單位所有，甚至，應該公開其原始程式碼。",
    "id": "387816094628136_618813208195089",
    "updated_time": "2014-05-11T02:01:56+0000",
    "from": {
        "name": "周靜蓉",
        "id": "777368089125274"
    },
    "likes": {
        "summary": {
            "total_count": 46
        }
    },
    "comments": {
        "data": [
            {
                "created_time": "2014-05-07T17:02:42+0000",
                "from": {
                    "name": "Hsiao-hsien Yang",
                    "id": "10156175249445984"
                },
                "message": "是不是可以併到這則來討論？\nhttps:\/\/www.facebook.com\/groups\/g0v.general\/permalink\/618833984859678\/",
                "id": "618836764859400"
            },
            {
                "created_time": "2014-05-07T17:18:01+0000",
                "from": {
                    "name": "周靜蓉",
                    "id": "777368089125274"
                },
                "message": "是該討論範圍沒錯，請問那算是一個專案嗎？",
                "id": "618843154858761"
            },
            {
                "created_time": "2014-05-07T17:19:34+0000",
                "from": {
                    "name": "Hsiao-hsien Yang",
                    "id": "10156175249445984"
                },
                "message": "點進去看看啊！怎麼了嗎？",
                "id": "618843528192057"
            },
            {
                "created_time": "2014-05-07T17:20:22+0000",
                "from": {
                    "name": "周靜蓉",
                    "id": "777368089125274"
                },
                "message": "看了啊…那算是零時政府的一個專案嗎？",
                "id": "618843708192039"
            },
            {
                "created_time": "2014-05-07T17:21:09+0000",
                "from": {
                    "name": "Hsiao-hsien Yang",
                    "id": "10156175249445984"
                },
                "message": "網址不是有寫 g0v？我無法很確定回答妳問的「一個專案」，因為這是之前某坑（專案）延伸，坑坑相連也可算同坑之延伸。",
                "id": "618843911525352"
            },
            {
                "created_time": "2014-05-07T17:33:16+0000",
                "from": {
                    "name": "Ly Cheng",
                    "id": "10155367657647883"
                },
                "message": "http:\/\/blog.clkao.org\/post\/197394\/uk-gds-the-veto-power 可以參考這篇 clkao去取經回來的成果, 這是我們可以去努力的方向, 可能要想一些方法縮短這個目標達成的距離, 例如實際投標及參與政府標案 :)",
                "id": "618848104858266"
            },
            {
                "created_time": "2014-05-08T01:39:29+0000",
                "from": {
                    "name": "Wen-Chi Cheng",
                    "id": "10156311430844284"
                },
                "message": "問題是承辦人員往往沒有這種觀念，只能乖乖給錢任人宰割；甚至有時想要求甚麼原本就該包含的功能，還會再被敲一筆\n~然後花大錢委外建立出來的系統，廠商還可以轉賣給好幾個有同樣需求的機關，而且都是以重新開發的價錢來賣",
                "id": "618991421510601"
            },
            {
                "created_time": "2014-05-08T02:19:43+0000",
                "from": {
                    "name": "Isabel Hou",
                    "id": "10213666573392133"
                },
                "message": "但採購契約的範本似乎是以智財權歸屬機關為原則，在個案中被變更了嗎？",
                "id": "619001608176249"
            },
            {
                "created_time": "2014-05-08T10:26:01+0000",
                "from": {
                    "name": "周靜蓉",
                    "id": "777368089125274"
                },
                "message": "契約內容公開是重點",
                "id": "619097971499946"
            },
            {
                "created_time": "2014-05-09T05:04:25+0000",
                "from": {
                    "name": "Yang-Ho Chen",
                    "id": "10105992438821395"
                },
                "message": "可是專案開發的公司在台灣的小眾市場..比較難有open source可能比較好的觀念..想說辛苦寫的code白捐岀不是增加自己的競爭者嗎..不像矽谷的許多公司..靠open source活也為Open Source的主力..Ex: Linkedin, Twitter..因為知道不open source, 那個功具或平台就沒人用, 或出現一個會更好的open source 把自己開發的比下去..自己公司也沒辦法活..所以必須靠結合眾人力開發好功具..",
                "id": "619457471463996"
            },
            {
                "created_time": "2014-05-09T05:10:40+0000",
                "from": {
                    "name": "Yang-Ho Chen",
                    "id": "10105992438821395"
                },
                "message": "簡單的來說, Ecosystem使一些廠商, 因為對長期自身發展有好處 Open Source ..獨霸的項目, Google\/Microsoft絕不開放..以政府的標案來說..要促使政府標案中規定open source. 需要的努力還很多",
                "id": "619460251463718"
            },
            {
                "created_time": "2014-05-10T18:16:30+0000",
                "from": {
                    "name": "Yu-Hsiang Huang",
                    "id": "10155862200640169"
                },
                "message": "其實每年高普考都有資訊類科，考的科目不外乎程式設計、作業系統、資料庫等等。套句某位高考的出題老師說過的話：“出那麼專業的題目有什麼用？那些人到頭來還不是只管發包”。現在的政府資訊類公務人員連發包都做不好，包案要如何測試，要如何驗收，全都沒人搞的清楚。我覺得整個政府的選才機制已經有問題，加上官僚體制的腐化，如果沒人大刀闊斧的改革，總統不管換誰當都會一樣爛。",
                "id": "620161848060225"
            },
            {
                "created_time": "2014-05-11T02:01:56+0000",
                "from": {
                    "name": "Wen-Chi Cheng",
                    "id": "10156311430844284"
                },
                "message": "因為資訊業務不是會寫程式就可以做的，後面有一大堆行政程序要跑，然後又要居中協調很多事情，甚至有時上面已經跟廠商講好要開發甚麼東西了，你又能怎樣?\n按理那些發包、驗收的程序，應該是採購、主計單位要協助，但往往行政單位都會烙一句說它們不懂資訊，所以承辦人員就要連這些都要懂；如果上面又已經有既定政策，這個XX系統已經講好要給誰做了，那下面就算發現有啥問題，提了啥建議，也只是蚊子叮牛角而已",
                "id": "620319048044505"
            }
        ],
        "summary": {
            "total_count": 13
        }
    }
}