{
    "created_time": "2013-12-06T11:54:05+0000",
    "message": "預告：g0v.tw hackath6n | 台灣零時政府第陸次勞動基準黑客松，下週一中午開放報名\n\n https:\/\/kktix.com\/events\/g0v-hackath6n",
    "story": "ET Blue shared a post to the group: g0v.tw 後勤中心.",
    "id": "387816094628136_549829055093505",
    "link": "https:\/\/kktix.com\/events\/g0v-hackath6n",
    "description": "【為何要來】g0v.tw 滿一週年了！一年來大家從零開始，打造各式資訊透明化平台[1]，在實作串連、挖坑填坑的過程中，也凝聚出新的參與社會的模式。除了生氣翻桌，真的有太多事可以作，黑客松就是能量反應爐，每隔兩個月我們一起衝刺一下！那麼來吧，帶著你的專業、你的想法、你的幹勁，準備一整天的黑客馬拉松。",
    "name": "g0v.tw hackath6n | 台灣零時政府第陸次勞動基準黑客松",
    "picture": "https:\/\/external.xx.fbcdn.net\/safe_image.php?d=AQBm1sh62LJ8B2ET&w=130&h=130&url=https%3A%2F%2Fkkbox-registrano.s3.amazonaws.com%2Fupload_images%2F13832%2F_____2013-12-06___12.22.30.png&cfs=1&_nc_hash=AQDal_mf-VzcsKZu",
    "updated_time": "2013-12-16T08:50:29+0000",
    "caption": "kktix.com",
    "from": {
        "name": "ET Blue",
        "id": "10212097510645743"
    },
    "likes": {
        "summary": {
            "total_count": 31
        }
    },
    "comments": {
        "data": [
            {
                "created_time": "2013-12-06T12:58:48+0000",
                "from": {
                    "name": "Hsiao-wei Chiu",
                    "id": "10215521254163616"
                },
                "message": "我覺得大家還是會跟上次一樣，到週一自己報到名才開始轉貼 XD",
                "id": "549848258424918"
            },
            {
                "created_time": "2013-12-09T02:46:11+0000",
                "from": {
                    "name": "陳彥佑",
                    "id": "10155053919762274"
                },
                "message": "真der~",
                "id": "550989184977492"
            },
            {
                "created_time": "2013-12-14T06:17:15+0000",
                "from": {
                    "name": "Chun-Ting Yeh",
                    "id": "10156108021954264"
                },
                "message": "請問沒搶到票有現場報名嗎 謝謝!",
                "id": "553246874751723"
            },
            {
                "created_time": "2013-12-14T06:30:32+0000",
                "from": {
                    "name": "ET Blue",
                    "id": "10212097510645743"
                },
                "message": "通常活動前一兩天會有些臨時不能來的名額釋出，可以等等看不用急 XD",
                "id": "553249294751481"
            },
            {
                "created_time": "2013-12-14T06:35:47+0000",
                "from": {
                    "name": "Hsiao-wei Chiu",
                    "id": "10215521254163616"
                },
                "message": "沒有現場報名喔～ 但報名時間開到當天早上09:00，還是請訂票。",
                "id": "553250188084725"
            },
            {
                "created_time": "2013-12-16T01:30:53+0000",
                "from": {
                    "name": "Max Yang",
                    "id": "2007561755925011"
                },
                "message": "臨時有事去不了，請問如何退票釋出名額，之前有看到LINK<但是後來找不到了",
                "id": "554013401341737"
            },
            {
                "created_time": "2013-12-16T03:03:42+0000",
                "from": {
                    "name": "Hsiao-wei Chiu",
                    "id": "10215521254163616"
                },
                "message": "Yang Max 參與活動頁面按下去，再按「現在就報名」，最下面有取消鍵。",
                "id": "554035748006169"
            },
            {
                "created_time": "2013-12-16T04:41:47+0000",
                "from": {
                    "name": "Max Yang",
                    "id": "2007561755925011"
                },
                "message": "瞿筱葳找不到耶\\只有  抱歉，目前本活動已額滿。",
                "id": "554054084671002"
            },
            {
                "created_time": "2013-12-16T07:04:01+0000",
                "from": {
                    "name": "Hsiao-wei Chiu",
                    "id": "10215521254163616"
                },
                "message": "Yang Max 請問你的報名序號？（在「瀏覽詳細資料」欄）需要的話手動幫刪....",
                "id": "554078734668537"
            },
            {
                "created_time": "2013-12-16T07:15:49+0000",
                "from": {
                    "name": "Max Yang",
                    "id": "2007561755925011"
                },
                "message": "@瞿筱葳  報名序號99",
                "id": "554080238001720"
            },
            {
                "created_time": "2013-12-16T07:18:30+0000",
                "from": {
                    "name": "ET Blue",
                    "id": "10212097510645743"
                },
                "message": "Yang Max 用你的 email 登入 kktix 以後再按「現在就報名」按鈕看看？ XD 登入畫面 https:\/\/kktix.com\/login ……噢，看來好像當初報名時就沒登入的樣子",
                "id": "554080554668355"
            },
            {
                "created_time": "2013-12-16T07:27:56+0000",
                "from": {
                    "name": "Max Yang",
                    "id": "2007561755925011"
                },
                "message": "當時的確是未加入 kktix， 加入後也是 報滿了",
                "id": "554081934668217"
            },
            {
                "created_time": "2013-12-16T08:50:29+0000",
                "from": {
                    "name": "Hsiao-wei Chiu",
                    "id": "10215521254163616"
                },
                "message": "所以....是kktix bug? 沒登入報名無法取消？cc WangShen Lu",
                "id": "554101961332881"
            }
        ],
        "summary": {
            "total_count": 13
        }
    }
}