{
    "created_time": "2015-06-19T16:02:01+0000",
    "message": "台灣不知道有沒有類似的數據? 平均房價\/租金數據比較容易取得，不知道跟住戶收入平均or中位數對照會不會有好玩的觀察角度?",
    "story": "Wu-Hsi Li shared Kai Chi Leung 梁啟智's photo to the group: g0v.tw 後勤中心.",
    "id": "387816094628136_821656264577448",
    "link": "https:\/\/www.facebook.com\/kaichil\/photos\/a.594779517226055.1073741828.594642803906393\/864632300240774\/?type=3",
    "description": "《港鐵沿線屋苑住戶月入中位數》\n\n早陣子有人問：香港人即使月入三萬也過得很難。但是，香港地，月入三萬其實已經相當不錯。借用之前大受歡迎的港鐵沿線呎價圖，這次和各位分享住戶每月收入中位數的統計。以寶翠園為例，有一半的住戶月入少於93580，另一半則是高於93580，至於高多少則無從得知。香港貧富懸殊，和你說堅尼系數未必易懂，看看隔一條街收入可以差幾倍，這應該相當清楚了。\n\n研究方法：數據來自2011年人口普查。入選屋苑居住人數必須高於3000人或住戶數目必須多於1000個。以港鐵站上蓋屋苑為代表，如無上蓋屋苑則以二百五十米範圍內人口最多的屋苑為代表。如兩者皆無，則以港鐵站所處的區議會選區為代表。\n\nhttp:\/\/www.census2011.gov.hk\/tc\/major-housing-estates.html\n\n黑字：私人屋苑或資助出售屋苑\n藍字：資助出租屋苑（包括已售單位）\n綠字：區議會選區\n\n港鐵合共 87 個站，已盡量覆核數據，如仍有錯誤，懇請見諒。\n\n6月15日更新\n1. 漏了南昌站 富昌邨 11040\n2. 有人問最高和最低在什麼地方，其實兩者都不在港鐵沿線。最高的是南區貝沙灣 157000 ，最低的是屯門寶田邨 6500 ，兩者差 24 倍。",
    "name": "Kai Chi Leung 梁啟智",
    "picture": "https:\/\/scontent.xx.fbcdn.net\/v\/t1.0-0\/s130x130\/10300505_864632300240774_187925478028163868_n.png?oh=5f6e1a231112355478fc958faf8a989c&oe=5B236A97",
    "updated_time": "2015-06-19T16:02:01+0000",
    "from": {
        "name": "Wu-Hsi Li",
        "id": "10101512795347798"
    },
    "likes": {
        "summary": {
            "total_count": 11
        }
    },
    "comments": {
        "data": [],
        "summary": {
            "total_count": 0
        }
    }
}