{
    "created_time": "2019-06-08T00:40:16+0000",
    "message": "Facing the Ocvean Meet & Hack\n#CodeForJapan #g0vtw #Parti\n#JP #KR #TW\n\n",
    "id": "387816094628136_2210702245672836",
    "link": "https:\/\/youtu.be\/yJTxKNsWpBE",
    "name": "Facing the Ocvean Meet & Hack",
    "picture": "https:\/\/external.xx.fbcdn.net\/safe_image.php?d=AQBAHJsHMob9tYGs&w=130&h=130&url=https%3A%2F%2Fi.ytimg.com%2Fvi%2FyJTxKNsWpBE%2Fhqdefault_live.jpg&cfs=1&_nc_hash=AQA1y5tBn7FwMsaM",
    "updated_time": "2019-06-08T06:05:16+0000",
    "caption": "youtube.com",
    "likes": {
        "summary": {
            "total_count": 14
        }
    },
    "comments": {
        "data": [
            {
                "created_time": "2019-06-08T02:29:39+0000",
                "message": "請問有 2019 FTO Meet & Hack info Sheet 連結嗎？",
                "id": "2210838278992566"
            },
            {
                "created_time": "2019-06-08T06:05:00+0000",
                "message": "Talks https:\/\/www.youtube.com\/c\/g0vTW\/live",
                "id": "2211074418968952"
            }
        ],
        "summary": {
            "total_count": 2
        }
    }
}