{
    "created_time": "2014-05-21T01:17:43+0000",
    "message": "大家好 我們是一群長年推動十八歲投票權的青少年公民團體\n最近正式啟動相關連署及修正憲法130條的行動\n同時將要在年底結合七合一選舉舉辦給16-20歲尚無投票權的\"青少年投票日\"\n由於我們缺乏網站技術及宣傳人員\n因此很希望能有人可以幫我們針對十八歲投票權議題接下來的文宣策略 \n以及製作懶人包\n還有年底將會舉辦的\"青少年投票日\" 需要開發相關網站介面\n給16-20歲青少年進行網路與實體投票 \n不知可否有機會可以跟G0V的夥伴們一起合作?",
    "story": "Ta-Hua Yeh shared 台灣少年權益與福利促進聯盟's photo to the group: g0v.tw 後勤中心.",
    "id": "387816094628136_625040504239026",
    "link": "https:\/\/www.facebook.com\/youthright\/photos\/a.138628868458.112480.120335638458\/10152387141398459\/?type=3",
    "description": "歡迎大家加入連署「支持世代正義，從18歲投票權開始」\n\n重點提示：\nA. 如果一個人大到可以打仗、納稅、組家庭，他\/她就應該可以投票\nB. 20歲投票權獨後全球，淪為民主後段班\n\n連署網站 https:\/\/sites.google.com\/site\/18vote\/\n\n呼籲各界連署支持響應：\n\n1. 行政院應組成「降低投票年齡推動小組」，研議如何落實「公民政治國際公約」第25條排除投票障礙之積極措施，推動18歲投票權。\n\n2. 立法院應啟動修憲程序，針對現行《憲法》第130條「中華民國國民年滿二十歲者，有依法選舉之權。」之投票年齡，及《公民投票法》投票年齡等一併下修至18歲，以達成權利義務對等、符合「世代正義」的民主社會。\n\n連署後，別忘了到「投票正義，十八開始」粉絲專業按讚，持續關注下修投票年齡。\nhttps:\/\/www.facebook.com\/18vote",
    "name": "台灣少年權益與福利促進聯盟",
    "picture": "https:\/\/scontent.xx.fbcdn.net\/v\/t1.0-0\/s130x130\/10312977_10152387141398459_4160007746470564082_n.jpg?oh=66be19feb5303c843b53e623079e289f&oe=5B13C4AB",
    "updated_time": "2014-05-22T12:34:33+0000",
    "from": {
        "name": "Ta-Hua Yeh",
        "id": "10209316831111735"
    },
    "likes": {
        "summary": {
            "total_count": 34
        }
    },
    "comments": {
        "data": [
            {
                "created_time": "2014-05-21T01:23:13+0000",
                "from": {
                    "name": "宋岡哲",
                    "id": "1383824905061339"
                },
                "message": "先說，我不支持這個，原因在這：\nhttps:\/\/www.facebook.com\/explorer09.kc\/posts\/532526433524528",
                "id": "625041950905548"
            },
            {
                "created_time": "2014-05-21T01:45:21+0000",
                "from": {
                    "name": "Ta-Hua Yeh",
                    "id": "10209316831111735"
                },
                "message": "了解!我們尊重您的意見 但民法年齡下修與刑法年齡一致也是我們的推動目標 民法當年訂定的社會背景與脈絡 與我國立法者的家父長及親權主義有極大關連性  這部分更難突破 最主要要看的是既然刑法上規定18歲要負完全刑事責任 但民法相關規定卻又要延後到20歲 是很錯亂的法制體例 這也是當今為何會造成各界批評的青少年公民權權利義務不對等的矛盾現象 並非只因各國的情形.此外 本人曾經發表於內政部社區發展季刊的一篇文章也供您參考與了解我們長年的思考https:\/\/www.facebook.com\/notes\/ta-hua-yeh\/%E4%B8%8D%E5%86%8D%E5%8F%AA%E6%98%AF%E7%A6%8F%E5%88%A9%E4%BE%9D%E8%B3%B4%E8%80%85%E5%BE%9E%E5%85%92%E5%B0%91%E6%AC%8A%E7%9B%8A%E6%96%B0%E6%B3%95%E7%9C%8B%E5%85%92%E5%B0%91%E7%9A%84%E5%85%AC%E6%B0%91%E6%AC%8A%E5%88%A9\/10201344932739258",
                "id": "625049074238169"
            },
            {
                "created_time": "2014-05-21T01:50:27+0000",
                "from": {
                    "name": "宋岡哲",
                    "id": "1383824905061339"
                },
                "message": "@Ta-Hua Yeh 你只是反親權主義這樣就把投票年齡下修？Damn you. 你們不會讓台灣更民主，你們這樣子只是把台灣的民主毀掉。",
                "id": "625050810904662"
            },
            {
                "created_time": "2014-05-21T01:53:56+0000",
                "from": {
                    "name": "Ta-Hua Yeh",
                    "id": "10209316831111735"
                },
                "message": "請看一下 我說的是:民法當年訂定的社會背景與脈絡 與我國立法者的家父長及親權主義有極大關連性 並沒有說我因反親權主義這樣就把投票年齡下修 這是很大的誤會ㄡ",
                "id": "625051987571211"
            },
            {
                "created_time": "2014-05-21T01:56:08+0000",
                "from": {
                    "name": "宋岡哲",
                    "id": "1383824905061339"
                },
                "message": "Ta-Hua Yeh 民法當年親權主義又怎樣？你們沒有告訴我一個正當的理由為什麼是18而不是16或17？",
                "id": "625052780904465"
            },
            {
                "created_time": "2014-05-21T02:04:32+0000",
                "from": {
                    "name": "Garfieros Po",
                    "id": "1887696104576146"
                },
                "message": "連問題都問得有夠怪，不用理他喇~",
                "id": "625055427570867"
            },
            {
                "created_time": "2014-05-21T02:06:41+0000",
                "from": {
                    "name": "宋岡哲",
                    "id": "1383824905061339"
                },
                "message": "Garfi Eros 你們不代表正義！就這樣！",
                "id": "625056887570721"
            },
            {
                "created_time": "2014-05-21T02:09:17+0000",
                "from": {
                    "name": "Garfieros Po",
                    "id": "1887696104576146"
                },
                "message": "(自稱代表正義的應該是自大到無以復加以為自己就是神~)\n(說別人不代表正義大概就是一個只能靠否定別人來肯定自己的卑微心態而已)",
                "id": "625058017570608"
            },
            {
                "created_time": "2014-05-21T03:04:27+0000",
                "from": {
                    "name": "Hsiao-wei Chiu",
                    "id": "10215521254163616"
                },
                "message": "贊成反對訴求可到該議題專頁，這裡以g0v後勤專案討論為主，對製作網頁懶人包等有興趣可討論如何協作支援。",
                "id": "625073394235737"
            },
            {
                "created_time": "2014-05-21T03:08:39+0000",
                "from": {
                    "name": "Ta-Hua Yeh",
                    "id": "10209316831111735"
                },
                "message": "謝謝，我們是來尋求大家協助的",
                "id": "625074580902285"
            },
            {
                "created_time": "2014-05-21T03:17:15+0000",
                "from": {
                    "name": "Hsiao-wei Chiu",
                    "id": "10215521254163616"
                },
                "message": "g0v討論以及與會有行為守則，請大家一起遵守，注意討論使用的語言。http:\/\/goo.gl\/96rvhk",
                "id": "625076870902056"
            },
            {
                "created_time": "2014-05-21T04:08:11+0000",
                "from": {
                    "name": "Shawn Lin",
                    "id": "10105835842002922"
                },
                "message": "因為18歲通常是高中職畢業升大學的年齡。\n對大學體制設計而言，如可以把所有的學生都當成人對待，不用甩家長，應該可減少一些媽寶與皮德潘的學生與畢業生。",
                "id": "625090584234018"
            },
            {
                "created_time": "2014-05-21T05:31:19+0000",
                "from": {
                    "name": "Sheng-Feng Huang",
                    "id": "10215528140826327"
                },
                "message": "上面這位宋岡哲先生反對將投票年齡下修到 18 歲，原因是民法上完全行為能力的年齡是訂在 20 歲，不過刑法上的完全責任能力年齡是 18 歲。行政罰法上的完全責任能力年齡是 18 歲。兒童及少年福利與權益保障法中規定的少年是 18 歲以下。\n\n所以，這代表甚麼？年滿 18 歲未滿 20 歲的人要負完全的刑事、行政責任，不受兒少法保護，但民法上又不被當成成年人，不能完全自主自己的經濟活動，然後連投票都沒資格。這不是三等公民什麼是三等公民？\n\n宋先生因為民法完全行為能力定在 20 歲所以反對將投票年齡降到 18 歲，卻又無視刑法、行政法及兒少法上的完全行為能力定在 18 歲的事實，請問，投票年齡只能跟民法成年年齡綁定不能與刑法、行政法、兒少法成人年齡綁定的理由何在？\n\n投票是決定自己的政治態度的行為，是選擇代議士參與政治的行為。今天代議士立法讓年滿１８歲未滿２０歲的人有責（行政、刑事）、無權（民法、不受兒少法保護），卻不允許這群受影響的人透過選票對代議士表達意見？所以宋先生是公然支持製造次等國民的意思？\n\n宋先生如果要以「沒有給一個合理理由」來反對將投票年齡降到 18 歲，不能因為「別國都這樣做」，那麼請問民法當年將成年年齡定在 20 歲又是甚麼理由？我唯一可以想像得到的理由就是「２０歲是男子弱冠之年」，而在中國傳統觀念裡「只有男人才是完整的人」，所以以傳統男人的成年年齡為民法上的成年年齡。\n\n事實上，在民法的完全行為能力上，目前美國、英國、德國、瑞士以及多數的歐陸國家都定在18歲，就連中華人民共和國都定在 18 歲，中華民國政府還維持在 20 歲是甚麼意思？在它統治之下的人民比較蠢笨？要比其他國家的人多活兩年才能有成熟的判斷能力？\n\n目前統治臺灣的中華民國政府一直以來都是法律制度的繼受國（怕你看不懂，就是抄別國的法律啦！），其他國家的法律制度一直都是重要的參考對象。如果不能因為「別國都這樣做」就這樣做，現在的中華民國法律裡面至少有九成五要廢掉。\n\n最後，日本眾議院已經通過國民投票法（公投法）修正案，決議將公投投票年齡在修法通過 4 年後降到 18 歲，同時在修正案附則中規定，於修正案施行後盡快就將民法成年年齡及一般公職選舉投票年齡降到 18 歲進行檢討。\nhttp:\/\/www.huffingtonpost.jp\/2014\/05\/08\/public-vote-issues_n_5286597.html",
                "id": "625116407564769"
            },
            {
                "created_time": "2014-05-22T00:19:17+0000",
                "from": {
                    "name": "宋岡哲",
                    "id": "1383824905061339"
                },
                "message": "",
                "id": "625469304196146"
            },
            {
                "created_time": "2014-05-22T02:15:34+0000",
                "from": {
                    "name": "Bo-chiuan Chen",
                    "id": "10215924811255492"
                },
                "message": "樓上不妨試請60～65歲的台北市民列舉雙方政見？此外，連選舉公報都還沒有出來，台灣也不只台北市，到底是準備好了什麼。",
                "id": "625534784189598"
            },
            {
                "created_time": "2014-05-22T02:39:04+0000",
                "from": {
                    "name": "Steve Good-Jobs",
                    "id": "10215495816529765"
                },
                "message": "嗯...我在想的是，無論20歲是否下修到18歲、還是國中畢業的16歲，前提是獨立思考以及冷靜理性判斷的必備要素是否已完成。\n\n看到這議題拋出時，我會想到的是：是否因為大部分政黨票倉來源的年紀大多為中老年人且做出往往不如另一群人預期的事？才需要一股新的力量來制衡？才需要這群剛從少年變青年的「輕青年」階層也參與？\n\n假設：這股新的力量參與了投票，但是結果不如你們原本的預期，如也支持與你們反方立場觀點的政黨，你們會採取的態度是開放不干涉、還是會想要強加控制灌輸觀念？\n原本目的是想讓更多公民參與？還是變成某目的的操作工具？\n（因為資料來源從該粉絲團尚無法得知，請多包涵）\n\n還是假使國外的公民政治國際公約能開放18歲參與投票，而這些國家的教育跟我們的教育上是否有什麼必要條件的不同？\n\n個人只是覺得，重點不在於年齡，無論是18~108歲，而在於獨立自主冷靜判斷的能力準備好沒？\n\n另一想法，讓18歲參與投票，或是讓20歲以上的我們如何更加學習自主判斷決定未來，我想這可能是更需要關注的議題。\n\n一點小困惑，歡迎支持的人協助理性回覆:))",
                "id": "625542127522197"
            },
            {
                "created_time": "2014-05-22T03:08:44+0000",
                "from": {
                    "name": "Anthony Liu",
                    "id": "10157089581674992"
                },
                "message": "個人認為, G0V 唯一的立場就是資料要公開, 易讀\n\n投票權要設定在 8 歲或 18 歲的討論, 應該是在別的地方, 主張將投票權修到 18 歲者, 由於要推行主張, 來這邊尋求願意幫忙的朋友支援技術, 當然可以, 反對的人, 也可以自己推動一個運動, 尋求所需要的技術協助.",
                "id": "625550304188046"
            },
            {
                "created_time": "2014-05-22T06:04:45+0000",
                "from": {
                    "name": "Ta-Hua Yeh",
                    "id": "10209316831111735"
                },
                "message": "目前不知道有誰願意幫我們填坑？",
                "id": "625592110850532"
            },
            {
                "created_time": "2014-05-22T09:49:12+0000",
                "from": {
                    "name": "黃冠儒",
                    "id": "1527718633992473"
                },
                "message": "男滿18歲，女滿16歲 父母同意就可以結婚 為何不能投票 請支持 投票正義，十八開始",
                "id": "625648140844929"
            },
            {
                "created_time": "2014-05-22T10:08:20+0000",
                "from": {
                    "name": "Hsiao-wei Chiu",
                    "id": "10215521254163616"
                },
                "message": "Andrew Huang 看起來是支持此立場，要填坑嗎？\n相關討論可到該議題粉絲頁，這邊還是聚焦討論坑。",
                "id": "625657674177309"
            },
            {
                "created_time": "2014-05-22T10:10:38+0000",
                "from": {
                    "name": "黃冠儒",
                    "id": "1527718633992473"
                },
                "message": "哈哈 好呀 看什麼需要幫忙的 會安排 跟青少年聊聊 問問他們的想法意見",
                "id": "625659544177122"
            },
            {
                "created_time": "2014-05-22T10:13:21+0000",
                "from": {
                    "name": "Hsiao-wei Chiu",
                    "id": "10215521254163616"
                },
                "message": "Ta-Hua Yeh 坑形可能要再挖清楚一點，開個 hackpad 寫一下具體想法及需求，或準備到6\/21黑客松提案。\nhttps:\/\/g0v.hackpad.com\/--aCZGg48I5pX 可以複製這個空白模版，寫一份簡單說明，這樣比較容易人坑合一。",
                "id": "625660100843733"
            },
            {
                "created_time": "2014-05-22T12:34:33+0000",
                "from": {
                    "name": "Ta-Hua Yeh",
                    "id": "10209316831111735"
                },
                "message": "非常感謝！已經有人來熱心的幫忙填坑了",
                "id": "625695540840189"
            }
        ],
        "summary": {
            "total_count": 23
        }
    }
}