{
    "created_time": "2012-12-01T06:40:09+0000",
    "message": "https:\/\/docs.google.com\/document\/d\/1HiJn1W30dFJaaAdxixJ-efwAphWN6nRaJdEKIMQwFzE\/edit",
    "story": "Kirsten Liu shared a link to the group: g0v.tw 後勤中心.",
    "id": "387816094628136_387816764628069",
    "link": "https:\/\/docs.google.com\/document\/d\/1HiJn1W30dFJaaAdxixJ-efwAphWN6nRaJdEKIMQwFzE\/edit",
    "name": "g0v 文案s - Google Drive",
    "updated_time": "2012-12-02T11:52:20+0000",
    "caption": "docs.google.com",
    "from": {
        "name": "Kirsten Liu",
        "id": "10155360770811527"
    },
    "likes": {
        "summary": {
            "total_count": 4
        }
    },
    "comments": {
        "data": [
            {
                "created_time": "2012-12-02T11:49:18+0000",
                "from": {
                    "name": "Minna Liu",
                    "id": "10155073313941898"
                },
                "message": "剛看過第一版文案只能說各位真的太強了~",
                "id": "388238881252524"
            },
            {
                "created_time": "2012-12-02T11:51:49+0000",
                "from": {
                    "name": "Kirsten Liu",
                    "id": "10155360770811527"
                },
                "message": "不敢當不敢當, 因為昨天文案寫手有資工人(我), 也有心理人(Crys), 剛好可以互補: D",
                "id": "388239414585804"
            },
            {
                "created_time": "2012-12-02T11:52:20+0000",
                "from": {
                    "name": "Minna Liu",
                    "id": "10155073313941898"
                },
                "message": "(拍手)",
                "id": "388239504585795"
            }
        ],
        "summary": {
            "total_count": 3
        }
    }
}