{
    "created_time": "2014-06-20T00:03:44+0000",
    "message": "各位好，我與一些朋友 (我們非程式資料專業，而是屬於空間規劃領域) 關注於「公有土地」，它的【類型】【在哪裡】【被如何處理與被開發】等議題。\n\n【公有地大行動！】\n http:\/\/hackfoldr.org\/POPonFire\/\n\n目前製作了一份計畫說明噢！",
    "story": "Che Wei Liu shared a link to the group: g0v.tw 後勤中心.",
    "id": "387816094628136_639505042792572",
    "link": "http:\/\/www.slideshare.net\/MikLiu\/20140620-36086988?utm_source=ss&utm_medium=upload&utm_campaign=quick-view",
    "description": "為什麼要關心 公有土地 總量變少了！被賣掉！ 用的怪怪的！變超怪！ 近20年來面積約10%私有化 例如，蓋出許多蚊子館 因為",
    "name": "20140620 公有土地計畫 簡報初版",
    "picture": "https:\/\/external.xx.fbcdn.net\/safe_image.php?d=AQB04cYTxfpXRDT4&w=130&h=130&url=http%3A%2F%2Fcdn.slidesharecdn.com%2Fss_thumbnails%2F20140620-140619185942-phpapp01-thumbnail-4.jpg%3Fcb%3D1403222392&cfs=1&_nc_hash=AQAdL11zyGGOwoEz",
    "updated_time": "2014-08-17T21:00:13+0000",
    "caption": "slideshare.net",
    "from": {
        "name": "Che Wei Liu",
        "id": "10156142432594038"
    },
    "likes": {
        "summary": {
            "total_count": 54
        }
    },
    "comments": {
        "data": [
            {
                "created_time": "2014-06-20T23:11:44+0000",
                "from": {
                    "name": "Che Wei Liu",
                    "id": "10156142432594038"
                },
                "message": "",
                "id": "639967019413041"
            },
            {
                "created_time": "2014-06-20T23:53:53+0000",
                "from": {
                    "name": "Che Wei Liu",
                    "id": "10156142432594038"
                },
                "message": "火線上的公有土地\n\n這次是原地主捐贈作為議會，而今要以地上權開發為商業使用\n\n家族後代投書表達抗議\nhttp:\/\/mobile.n.yam.com\/m\/news.php?id=20140620368022",
                "id": "639977742745302"
            },
            {
                "created_time": "2014-06-23T17:24:15+0000",
                "from": {
                    "name": "Che Wei Liu",
                    "id": "10156142432594038"
                },
                "message": "from\nChung-hsin Yang 楊重信（文化大學景觀系教授）臉書\n\n請我的學生邊泰明「踹共」！\n台北市「全市性保護區處理原則」草案（「臺北市內湖區都市計畫通盤檢討（主要計畫）案」P.58之「保護區檢討原則」）到底是誰擬訂出來的？是台北市都發局嗎？請我的學生邊泰明「踹共」！邊泰明是受郝市長指示擬訂的嗎？或是揣測上意擬訂出來的嗎？或是揣測上人意擬訂出來的？或是都發局自主擬訂出來的？這麼重要的保護區變更原則，怎麼可以不經過審慎研究、民眾參與、以及衝擊評估，即草率、倉促地提到都委會？這麼重要的保護區變更原則經過都委會討論通過就可以嗎？\n\n強烈譴責台北市「全市性保護區處理原則」草案（「臺北市內湖區都市計畫通盤檢討（主要計畫）案」P.58之「保護區檢討原則」）為「慈濟內湖保護區變更案」與「薇格中學保護區變更案」量身定做！\n\n／\n\n#政策\n#變更\n#都市計畫\n#通盤檢討\n#保護區\n#台北市\n#都市發展局\n#慈濟\n#薇閣小學\n#板橋林家 薇閣小學的創設者\n#行義路溫泉\n#貓空\n#老泉里\n#楊重信 都市計畫學者\n#邊泰明 現任台北市都市發展局局長\n\n說明：慈濟與薇閣小學都是私有地，但這個保護區處理原則草案政策，會涵蓋更多公私有土地，所以就蠻相關，也顯示特定政策可能需要參照實際的內容才能夠判斷是否與公有土地相關聯\n\n／\n\nfrom\nChung-hsin Yang 楊重信（文化大學景觀系教授）臉書\n\n向背德政府宣戰！搶救台北市保護區！\n\n「全市性保護區處理原則」草案之原則3(3)與3(4)是為偽宗教家、偽慈善家、偽教育家、財團與營利業者量身定做的原則：\n\n原則3(3)：為發展文化、教育、慈善、醫療等公益使用需求，需利用保護區土地作為發展特定專用區使用，得將無潛在地質災害或環境敏感之保護區，檢討變更為特定專用區。\n\n原則3(4)：特有天然資源及地方產業特色聚落之保護區，為避免景觀凌亂及土地資源遭受污染及破壞，得檢討變更為特定專用區以 利有效管理，提升土地及資源之使用及環境管理效益。\n\n原則3(3)之「慈善公益使用需求」顯然是為「慈濟內湖保護區變更案」量身定作；「教育公益使用需求」顯然是為「薇閣中學保護區變更案」量身定作。\n\n原則3(4)之「特有天然資源」顯然是為「行義路溫泉業者」擴充用地鋪路；「地方產業特色聚落」可能在為類似「貓空」、「老泉里」等類聚落地區擴大發展範圍而鋪路。\n\n這個政府詭計多端，葫蘆裡可能裝了很多我們不認識的藥，請大家來腦力激盪，分析郝(是「郝」不是「好」！）要通過的「全市性保護區處理原則」，除了我剛提到的陽謀外，還有哪些陰謀！",
                "id": "641520579257685"
            },
            {
                "created_time": "2014-06-23T17:32:50+0000",
                "from": {
                    "name": "Finjon Kiang",
                    "id": "10211662005529746"
                },
                "message": "除此之外，也許可以考慮納入一些基於容積獎勵而畫為 \"公共開放空間\" 的土地，因為這類土地很多都還是被私人所佔用 ;)",
                "id": "641523069257436"
            },
            {
                "created_time": "2014-06-23T17:54:59+0000",
                "from": {
                    "name": "Che Wei Liu",
                    "id": "10156142432594038"
                },
                "message": "嗯嗯，目前還在找這類因為容積獎勵而生的「公共空間」(戶外開放、停車場、公益回饋設施...) 的資料來源",
                "id": "641530032590073"
            },
            {
                "created_time": "2014-06-23T18:21:29+0000",
                "from": {
                    "name": "Che Wei Liu",
                    "id": "10156142432594038"
                },
                "message": "#產業用地（有各種開發方式）\n#國發會\n#政策\n#出租\n#讓售\n#標售\n#BOT\n#設定地上權\n#合作開發\n\n國發會產業用地供給資訊平台\nhttp:\/\/ngis.nat.gov.tw\/iland\/mapSearch.aspx",
                "id": "641548115921598"
            },
            {
                "created_time": "2014-06-23T20:35:42+0000",
                "from": {
                    "name": "Dan Jacobson",
                    "id": "1687295634627092"
                },
                "message": "http:\/\/www.youtube.com\/watch?v=dG2rV717R_M&list=PLA5E14A18C19B57D8\n可問 地球公民基金會，\n為何國產暑好幾筆遭林務局退回…",
                "id": "641597695916640"
            },
            {
                "created_time": "2014-06-23T20:36:59+0000",
                "from": {
                    "name": "Dan Jacobson",
                    "id": "1687295634627092"
                },
                "message": "國產暑承租人不開放查…",
                "id": "641597992583277"
            },
            {
                "created_time": "2014-06-24T15:31:32+0000",
                "from": {
                    "name": "Che Wei Liu",
                    "id": "10156142432594038"
                },
                "message": "臺鐵公產",
                "id": "641983495878060"
            },
            {
                "created_time": "2014-06-24T17:47:22+0000",
                "from": {
                    "name": "Bohung Lin",
                    "id": "1558992637554896"
                },
                "message": "https:\/\/www.facebook.com\/photo.php?fbid=585595108227992&set=a.108988735888634.11278.100003325247529&type=1&theater",
                "id": "642039505872459"
            },
            {
                "created_time": "2014-06-27T17:36:08+0000",
                "from": {
                    "name": "Che Wei Liu",
                    "id": "10156142432594038"
                },
                "message": "",
                "id": "643584695717940"
            },
            {
                "created_time": "2014-06-30T15:16:14+0000",
                "from": {
                    "name": "Che Wei Liu",
                    "id": "10156142432594038"
                },
                "message": "https:\/\/m.facebook.com\/HuaKuang.our.home\/photos\/a.115145321994150.21170.114508315391184\/309786475863366\/?type=1&source=46\n\n「華光社區特定專用區細部計畫案專案小組」",
                "id": "645104792232597"
            },
            {
                "created_time": "2014-07-01T03:48:32+0000",
                "from": {
                    "name": "林亦",
                    "id": "1550076175029367"
                },
                "message": "https:\/\/www.facebook.com\/HuaTungVoice2011\/photos\/a.125255670872478.19464.123989320999113\/732647510133288\/?type=1&theater",
                "id": "645358032207273"
            },
            {
                "created_time": "2014-07-05T16:16:04+0000",
                "from": {
                    "name": "Shi Woo Hong",
                    "id": "10213855060303990"
                },
                "message": "被不當賣掉的 也應該試著爭取回來 政府應該做全面性的總檢討",
                "id": "647436501999426"
            },
            {
                "created_time": "2014-07-05T16:30:56+0000",
                "from": {
                    "name": "Hsiao-wei Chiu",
                    "id": "10215521254163616"
                },
                "message": "Annie Shih 看到你分享文，不過 clkao 和 freedom 是不同人呃。(sorry 你版無法留言）",
                "id": "647442558665487"
            },
            {
                "created_time": "2014-07-05T16:33:45+0000",
                "from": {
                    "name": "Shi Woo Hong",
                    "id": "10213855060303990"
                },
                "message": "好糗喔 這樣也會被發現喔！ 大哭",
                "id": "647444051998671"
            },
            {
                "created_time": "2014-07-05T16:35:46+0000",
                "from": {
                    "name": "Hsiao-wei Chiu",
                    "id": "10215521254163616"
                },
                "message": "噗因為你分享的是我貼的文（拍拍）",
                "id": "647448648664878"
            },
            {
                "created_time": "2014-07-05T17:15:45+0000",
                "from": {
                    "name": "Shi Woo Hong",
                    "id": "10213855060303990"
                },
                "message": "但是請問這篇不是Che Wei Liu的文嗎？",
                "id": "647465528663190"
            },
            {
                "created_time": "2014-08-17T13:37:50+0000",
                "from": {
                    "name": "Che Wei Liu",
                    "id": "10156142432594038"
                },
                "message": "目前的架構～\nhttp:\/\/hackfoldr.org\/POPonFire\/",
                "id": "667748136634929"
            },
            {
                "created_time": "2014-08-17T14:17:46+0000",
                "from": {
                    "name": "Che Wei Liu",
                    "id": "10156142432594038"
                },
                "message": "公有土地的四個面向：\n\n所有權\n測繪資料\n開發權\n規畫權",
                "id": "667762029966873"
            },
            {
                "created_time": "2014-08-17T21:00:13+0000",
                "from": {
                    "name": "Che Wei Liu",
                    "id": "10156142432594038"
                },
                "message": "全國區域計畫工作坊\nhttp:\/\/www.cet-taiwan.org\/node\/2002",
                "id": "667905973285812"
            }
        ],
        "summary": {
            "total_count": 21
        }
    }
}