{
    "created_time": "2015-06-28T06:12:13+0000",
    "story": "Finjon Kiang shared a link to the group: g0v.tw 後勤中心.",
    "id": "387816094628136_825317337544674",
    "link": "http:\/\/leechsien.github.io\/DustExplosions\/",
    "name": "八仙爆炸事件傷者查詢",
    "updated_time": "2015-06-28T06:14:41+0000",
    "caption": "leechsien.github.io",
    "from": {
        "name": "Finjon Kiang",
        "id": "10211662005529746"
    },
    "likes": {
        "summary": {
            "total_count": 31
        }
    },
    "comments": {
        "data": [
            {
                "created_time": "2015-06-28T06:14:41+0000",
                "from": {
                    "name": "Finjon Kiang",
                    "id": "10211662005529746"
                },
                "message": "http:\/\/www.gov.taipei\/ct.asp?xItem=108880666&ctNode=38161&mp=100001",
                "id": "825319257544482"
            }
        ],
        "summary": {
            "total_count": 1
        }
    }
}