{
    "created_time": "2014-03-20T18:11:15+0000",
    "message": "這是我今天錄到的影片，在濟南路上，四名警員想藉故直接進入立院，但警方並沒有先放出相對數目的警員，因而被包圍群眾檔下的過程，若ok再幫我轉發，感謝",
    "id": "387816094628136_596855457057531",
    "link": "https:\/\/www.facebook.com\/10155799145128564\/videos\/10152030210848564",
    "picture": "https:\/\/scontent.xx.fbcdn.net\/v\/t15.0-10\/s130x130\/1898483_10152030214403564_10152030210848564_11552_1627_b.jpg?oh=699f643b0ec76497b7fcd870525a7a44&oe=5ADBA130",
    "updated_time": "2014-03-20T18:11:15+0000",
    "from": {
        "name": "MarsZ Chen",
        "id": "10155799145128564"
    },
    "likes": {
        "summary": {
            "total_count": 54
        }
    },
    "comments": {
        "data": [],
        "summary": {
            "total_count": 0
        }
    }
}