{
    "created_time": "2014-04-16T16:30:54+0000",
    "message": "面對遍地開腸花, 推出直播祕技Free\n\n直播祕技(0417第二版)\n- 三種模式適合\n- 串流參數建議\n- 指向性麥克風\n\n直播祕技(0417第三版)\n- 機動防水直播台建置\n- 三種模式成果照\n- 簡報結尾加入吧！\n- BlackMagic mini Recorder\n\n---\n先出第一個版本 Chia-liang Kao",
    "story": "YuTin Liu shared a link to the group: g0v.tw 後勤中心.",
    "id": "387816094628136_608542419222168",
    "link": "http:\/\/www.slideshare.net\/yuting1987\/0417-33607269",
    "description": "直播祕技 幹",
    "name": "直播祕技(0417第一版)",
    "picture": "https:\/\/external.xx.fbcdn.net\/safe_image.php?d=AQALsl2kX6rkYD7G&w=130&h=130&url=http%3A%2F%2Fcdn.slidesharecdn.com%2Fss_thumbnails%2F0417-140416112301-phpapp01-thumbnail-4.jpg%3Fcb%3D1397665656&cfs=1&_nc_hash=AQA93kbHfYnSfFeS",
    "updated_time": "2014-04-18T03:35:50+0000",
    "caption": "slideshare.net",
    "likes": {
        "summary": {
            "total_count": 75
        }
    },
    "comments": {
        "data": [
            {
                "created_time": "2014-04-16T16:31:46+0000",
                "message": "簡短有力符合腸花!!! XD",
                "id": "608542709222139"
            },
            {
                "created_time": "2014-04-16T16:33:04+0000",
                "message": "說好的圖解自幹防雨戰力架呢？作個英文版的說明應該會 hn#1",
                "id": "608543022555441"
            },
            {
                "created_time": "2014-04-16T16:35:00+0000",
                "message": "ipad是不是有指定軟體？",
                "id": "608543569222053"
            },
            {
                "created_time": "2014-04-16T16:35:42+0000",
                "message": "簡單有力",
                "id": "608543859222024"
            },
            {
                "created_time": "2014-04-16T16:37:59+0000",
                "message": "Chia-liang Kao 明天來個組合起來的教學, 接著增加選配教學 kerker 然後在英文化",
                "id": "608544749221935"
            },
            {
                "created_time": "2014-04-16T16:39:21+0000",
                "message": "黃吉米 其實iPad用ustream.tv就好哩, 用youtube live要設定會瘋掉QQ",
                "id": "608545422555201"
            },
            {
                "created_time": "2014-04-16T16:40:15+0000",
                "message": "C875是什麼神物",
                "id": "608545722555171"
            },
            {
                "created_time": "2014-04-16T16:42:19+0000",
                "message": "C875是入門款 影像截取盒",
                "id": "608546422555101"
            },
            {
                "created_time": "2014-04-16T16:52:05+0000",
                "message": "劉宇庭 明明就可以直接下載 設定檔 開起來就可以上傳了!!",
                "id": "608550369221373"
            },
            {
                "created_time": "2014-04-16T16:58:09+0000",
                "message": "那個webcam圖  我有一隻一模一樣的XD",
                "id": "608552445887832"
            },
            {
                "created_time": "2014-04-16T17:00:19+0000",
                "message": "Ly Cheng 你的意思是說用notebook下載設定檔, 然後email到iPad再開起來嗎？還是可以直接從iPad下載開啓？",
                "id": "608552955887781"
            },
            {
                "created_time": "2014-04-16T17:02:57+0000",
                "message": "對哩～ Chia-liang Kao 防水架, 有個關鍵道具是『工業用保鮮膜』",
                "id": "608553625887714"
            },
            {
                "created_time": "2014-04-16T17:08:39+0000",
                "message": "在想 Sony Cyber-shot DSC-QX10 是否可以live streaming ( http:\/\/cdn.androidpolice.com\/wp-content\/uploads\/2013\/09\/nexusae0_wm__DSC3712.jpg )",
                "id": "608556015887475"
            },
            {
                "created_time": "2014-04-16T17:12:57+0000",
                "message": "黃吉米 拿來打高畫質應該不錯 kerker 不過這鏡頭拿久會酸... 也許適合用在行政院那天？",
                "id": "608557625887314"
            },
            {
                "created_time": "2014-04-16T17:15:27+0000",
                "message": "劉宇庭，好像得研究一下是否可直播...畢竟連線時已經吃掉裝置的 wifi",
                "id": "608558525887224"
            },
            {
                "created_time": "2014-04-16T17:16:33+0000",
                "message": "我帶去 g0v 的 DV 可以當 usb cam, 不過只能 320x240. 用 1394(firewire) 可以 640x480...不過沒人要用所以... http:\/\/www.amazon.com\/Panasonic-PV-GS500-Camcorder-Optical-Stabilized\/dp\/B000DZFUIO",
                "id": "608558989220511"
            },
            {
                "created_time": "2014-04-16T17:18:07+0000",
                "message": "Jimy Huang 那還有3g可以直播阿 XD",
                "id": "608559889220421"
            },
            {
                "created_time": "2014-04-16T17:18:38+0000",
                "message": "忘了說, 我的設備就是野草莓轉播組當時留下來的。改造過電線，所以DV可以用行動電源運作。",
                "id": "608560119220398"
            },
            {
                "created_time": "2014-04-16T17:21:31+0000",
                "message": "skywatch 這樣的設備也可以考慮 - https:\/\/www.skywatch24.com\/tw\/cams\/skywatch-cams ， http:\/\/ustream-helpers.com\/node\/138 這些好像直接就支援 ustream 了",
                "id": "608560935886983"
            },
            {
                "created_time": "2014-04-16T17:23:10+0000",
                "message": "ipcam 完全不行啦....orz",
                "id": "608561359220274"
            },
            {
                "created_time": "2014-04-16T17:23:53+0000",
                "message": "Tyler Lin why? 畫質？",
                "id": "608561579220252"
            },
            {
                "created_time": "2014-04-16T17:28:40+0000",
                "message": "ipcam 一臺多少，iPhone\/iPad 一臺多少? 電腦＋DV 價格又多少？ipcam cpu 弱，不適合畫面變動快速的環境。有用 iPhone 轉播的就知道轉播時手機很燙很耗電。webcam 晚上通常也不大行。",
                "id": "608562929220117"
            },
            {
                "created_time": "2014-04-16T17:30:54+0000",
                "message": "skywatch 這次的現場轉播，畫質差強人意，但多少可以印證它還是能夠滿足基本的直播需求？",
                "id": "608563729220037"
            },
            {
                "created_time": "2014-04-16T17:31:11+0000",
                "message": "另外收音其實對轉播來說非常重要，不過定點轉播比較沒這個需求。",
                "id": "608563792553364"
            },
            {
                "created_time": "2014-04-16T17:33:11+0000",
                "message": "只是這次 skywatch 不願意直接把 rtmp 接上 youtube （因為他們想藉這次機會去開發直播功能），但技術上應該可行。有這樣的設備至少可以降低固定直播區域的人力需求。",
                "id": "608564245886652"
            },
            {
                "created_time": "2014-04-16T17:34:17+0000",
                "message": "差點忘記聲音... @@\"",
                "id": "608564669219943"
            },
            {
                "created_time": "2014-04-16T17:34:25+0000",
                "message": "老實說... ipcam 還是當監視器就好...",
                "id": "608564699219940"
            },
            {
                "created_time": "2014-04-16T17:36:32+0000",
                "message": "就畫質而言\nYoutube live event > Hangouts On Air 吧??",
                "id": "608565319219878"
            },
            {
                "created_time": "2014-04-16T17:37:05+0000",
                "message": "-.-||, ipcam 沒這麼糟吧，至少像這次大量的民主講堂散落各地，有類似的設備就能夠完整收錄，不再需要大量專業設備或人介入。",
                "id": "608565515886525"
            },
            {
                "created_time": "2014-04-16T17:44:12+0000",
                "message": "我們以前做通常兩人一組，一個是主持人、另一個是場控。場控要負責鏡頭、網路監控、設備，還要回聊天室訊息。",
                "id": "608568139219596"
            },
            {
                "created_time": "2014-04-16T17:51:41+0000",
                "message": "收聲音和畫面都需要技巧... 今天是因為環境光線足，聲音都從喇叭附近收才不需要額外設備... 如果你是轉播抗議現場會發現畫面震動很厲害，這時候就需要防手震。如果附近不夠亮就會需要夜視功能。聲音的部分如果是在抗議現場沒什麼問題，但是研討會之類的時候就要找喇叭附近坐，不然會收不到音。很多記者的解決方法是把無線麥黏在喇叭上，這樣攝影機就可以找好角度拍攝。",
                "id": "608571395885937"
            },
            {
                "created_time": "2014-04-16T18:00:46+0000",
                "message": "畫面定住不動很難吸引人觀看，所以運鏡很重要。這是為什麼可以用 DV 就用 DV，真的不能用 DV 就用腳移動。",
                "id": "608574255885651"
            },
            {
                "created_time": "2014-04-16T18:10:52+0000",
                "message": "目前我想買這台可以透過 wifi 上 ustream 的 DV http:\/\/www.trustedreviews.com\/panasonic-hc-v720_Camcorder_review",
                "id": "608578109218599"
            },
            {
                "created_time": "2014-04-16T18:19:41+0000",
                "message": "Ly Cheng 請問在 iPad 上如何用 youtube live?",
                "id": "608586402551103"
            },
            {
                "created_time": "2014-04-16T18:43:29+0000",
                "message": "Tyler Lin 裝任何可以rtmp的app, 不過設定如 劉宇庭講的 我猜因為要輸入所以覺得麻煩? 我看broadcast me 是蠻簡單的 不過要錢",
                "id": "608598705883206"
            },
            {
                "created_time": "2014-04-16T18:44:31+0000",
                "message": "我差不多搞清楚了，果然是 rtmp :)",
                "id": "608599065883170"
            },
            {
                "created_time": "2014-04-16T18:45:29+0000",
                "message": "應該可以寫個install app 直接透過youtube live streaming api 去送 就不用這麼麻煩了 XDD",
                "id": "608599342549809"
            },
            {
                "created_time": "2014-04-17T02:39:35+0000",
                "message": "可惡 HC-X920 HC-V720 HC-520 台灣都沒賣,\nLivestream Broadcaster 和 Cerevo LiveShell 也不錯,\n但台灣都沒賣QQ 除非代購",
                "id": "608733222536421"
            },
            {
                "created_time": "2014-04-17T02:42:36+0000",
                "message": "HC-V720 日本有賣，型號稍微不同。",
                "id": "608733889203021"
            },
            {
                "created_time": "2014-04-17T02:54:54+0000",
                "message": "我比較想要blackmagicdesign的XD",
                "id": "608736395869437"
            },
            {
                "created_time": "2014-04-17T02:59:55+0000",
                "message": "其實我們要瞭解一件事：「錄影收音」跟「網路直播」是上下游關係。\n如果要講究直播品質，雖然因為頻寬與即時運算力，決定了影音編碼品質的上限，但 YouTube 上那些漂亮華麗的 1080p 電影預告片，編碼品質其實跟 YouTube Live 最高品質的 1080p, 30fps, 6000k+128k bps 也差不了多少。\n所以如果沒自備六位數以上的錄影收音硬體，是很難克服各種常見的「燈光、音響、位置」環境問題，去逼近、用盡編碼品質上限的。（當然如果環境硬體有為此設計考量，錄影收音設備的負擔就可以減低...）至於控管活動流程，搭配現場製作去符合觀眾資訊需求、觀看經驗的部份就更別提了...\n\n但回過頭來，社運直播需要什麼品質？公民記者或社運組織能負擔的設備是什麼？作為影音宅當然很難對這些直播的【觀看經驗】滿意，但作為關心時政的公民、支持資訊透明的 g0ver 來說，這些不同等級的簡陋直播套裝（即使只是 ipcam），至少有作到【公開存證、基本溝通】價值啦~",
                "id": "608737485869328"
            },
            {
                "created_time": "2014-04-17T04:02:51+0000",
                "message": "直播祕技(0417第二版)\n- 三種模式適合\n- 串流參數建議\n- 指向性麥克風",
                "id": "608753529201057"
            },
            {
                "created_time": "2014-04-17T04:02:57+0000",
                "message": "實況軟體有開放源碼的選擇，\nOpen Broadcaster Software (OBS)\nhttps:\/\/obsproject.com\/\n可以在Windows和Linux上跑",
                "id": "608753542534389"
            },
            {
                "created_time": "2014-04-17T04:05:33+0000",
                "message": "Bropheus Huang說的真好!!  凡事沒有萬靈丹, 見招拆招才是上策 XD",
                "id": "608754012534342"
            },
            {
                "created_time": "2014-04-17T04:07:56+0000",
                "message": "ipcam 在太陽花的行動裡, 也佔了很重要了很重要的角色, 不少事件的畫面就是靠ipcam所記錄的, 所以當時有提起行車記錄器的計劃.\n不過直播vs記錄, 在定位上還是有些差距.\n但話說回來任何方法, 只要能夠讓收視者看到想要的畫面都是好方法.",
                "id": "608754449200965"
            },
            {
                "created_time": "2014-04-17T04:37:59+0000",
                "message": "忽然看到大家有討論到Skywatch，這邊我解釋一下兩點，1.我們原本是在做雲端錄影的部分(plug n play不需要固定ip或開port 2.手機app skywatch view目前是rtsp不是rtmp 。\n立法院直播是臨時寫出來的網頁變成直播（廣播），畫質可達H264 1280x800 30fps 最高，同時雲端錄影存證。大家看到畫面差是因為頻寬差所以我們降畫質處理。\n正在努力直接寫成直播的app或是service site，但是要變成正式產品需要時間，這期間正在跟公司同仁討論能否用個臨時版。",
                "id": "608760619200348"
            },
            {
                "created_time": "2014-04-17T04:38:57+0000",
                "message": "要拉rtsp去給youtube這沒問題，但是需要開port跟ip那些，就減低了原本我們有vpn server去介接的方便性優勢了（plug n play)",
                "id": "608760762533667"
            },
            {
                "created_time": "2014-04-17T04:40:29+0000",
                "message": "另外收音的問題可以靠外接麥克風解決~ 我也正在研究測試中！希望可以趕出一個大家能快速架設的好東西",
                "id": "608760975866979"
            },
            {
                "created_time": "2014-04-17T04:41:45+0000",
                "message": "我們還是希望設備的訊號能夠直接上 ustream or youtube ，可以省去一些費用、維護與後製問題",
                "id": "608761155866961"
            },
            {
                "created_time": "2014-04-17T04:44:02+0000",
                "message": "應該有機會 我研究中",
                "id": "608761515866925"
            },
            {
                "created_time": "2014-04-17T04:44:56+0000",
                "message": "開 youtube event 的 api 昨天 Ly Cheng 試出來了: http:\/\/yhsiang.logdown.com\/posts\/2014\/04\/16\/stream-to-youtube-with-live-streaming-api",
                "id": "608761702533573"
            },
            {
                "created_time": "2014-04-17T04:46:42+0000",
                "message": "有沒有ios dev或android dev來開發 手機開直播app 吧 :)",
                "id": "608762202533523"
            },
            {
                "created_time": "2014-04-17T04:48:52+0000",
                "message": "打個廣告，目前我正在寫「第五權電視牆監看「評」台g8v.tv草案」\nhttps:\/\/g0v.hackpad.com\/g8v.tv-lk9pamtKwyr\n歡迎大家提供意見，如果一切順利會試著在419黑客松提案，\n有任何想法都歡迎在hackpad裡提出來 >:o",
                "id": "608762795866797"
            },
            {
                "created_time": "2014-04-17T05:51:46+0000",
                "message": "手機有 ustream app 可以直播。",
                "id": "608776985865378"
            },
            {
                "created_time": "2014-04-17T06:48:10+0000",
                "message": "劉宇庭, 因為 mac OS 下不能用 C875 \/ CV710... 這些 DirectShow 類的擷取器來配 camcorder，所以要不加個最低啟動的 BlackMagic mini Recorder ?",
                "id": "608789815864095"
            },
            {
                "created_time": "2014-04-17T06:49:53+0000",
                "message": "對！mac OS 請補 mini Recorder + Thunder bolt線... XDD",
                "id": "608790052530738"
            },
            {
                "created_time": "2014-04-17T06:53:33+0000",
                "message": "請問是這顆嗎？",
                "id": "608790619197348"
            },
            {
                "created_time": "2014-04-17T06:54:18+0000",
                "message": "對，美金 $149, 但台灣買就...",
                "id": "608790779197332"
            },
            {
                "created_time": "2014-04-17T06:55:20+0000",
                "message": "好～ 晚上第三版 會更新上去",
                "id": "608791345863942"
            },
            {
                "created_time": "2014-04-17T07:00:24+0000",
                "message": "據說強者我朋友新參這次大松會裝備一顆 GoPro",
                "id": "608800785862998"
            },
            {
                "created_time": "2014-04-17T07:05:57+0000",
                "message": "Bropheus Huang BlackMagic mini Recorder 是把HDMI訊號透過thunderbolt輸出到螢幕？還是能夠讓OSX內的軟體可以讀取到聲音及影像訊號？",
                "id": "608801875862889"
            },
            {
                "created_time": "2014-04-17T07:15:00+0000",
                "message": "把 HDMI \/ SDI 來源的影音訊號，經 thunderbolt 送往電腦，讓直播軟體如 hangout \/ wirecast \/ ustream producer 等可以讀到影音訊號、直播出去",
                "id": "608804439195966"
            },
            {
                "created_time": "2014-04-17T07:19:49+0000",
                "message": "BMD mini recorder 跟 C875 等，在直播中都是擷取器角色，只是支援功能與規格不同",
                "id": "608805355862541"
            },
            {
                "created_time": "2014-04-17T07:30:36+0000",
                "message": "了解哩^^ 而且用thunderbolt傳輸的效能比USB好, BMD mini recorder 有做編碼的動作嗎？ 要不然很吃NB的CPU.",
                "id": "608808969195513"
            },
            {
                "created_time": "2014-04-17T07:57:12+0000",
                "message": "blackmagic mini  recorder我看露天賣6600，\n我看應該可以問到認識的賣6000，有需要的話我覺得應該可以來開團購。",
                "id": "608814472528296"
            },
            {
                "created_time": "2014-04-17T07:58:08+0000",
                "message": "BMD 家是作 prosumer & 廣播級機器，硬壓的話最低價是 $149 video recorder（各種類比）和 $495 H.264 Pro Recorder（HDMI \/ SDI 等）",
                "id": "608814732528270"
            },
            {
                "created_time": "2014-04-17T08:00:34+0000",
                "message": "順便請教一下， BMD 的 pocket movie recorder 錄起來跟一般 DV or M4\/3系統DC，品質有好很多嗎？我知道他主打可以輸入剪輯資訊\/輕巧方便\/可換鏡頭\n\n如果quality沒有好到很多，買一個拍電影\/廣播設備來支援直播 \/ 黑客松 \/ 研討會錄影，好像沒什麼必要。 XDD",
                "id": "608815215861555"
            },
            {
                "created_time": "2014-04-17T08:04:04+0000",
                "message": "Macpaul Lin BMPCC 是超高位元率吃記憶卡怪物，保留高動態範圍、畫面細節，給電影調光創作用，不是直播取向的機器。真有興趣的話，下次在 BOOKSHOW 辦小松時可以來看 :3",
                "id": "608815945861482"
            },
            {
                "created_time": "2014-04-17T08:10:28+0000",
                "message": "Simon Pai GoPro 要裝頭上當人肉自走直播機 \/ 縮時錄影機嗎 XD",
                "id": "608816795861397"
            },
            {
                "created_time": "2014-04-17T08:12:12+0000",
                "message": "到時候問他 XD",
                "id": "608817062528037"
            },
            {
                "created_time": "2014-04-18T03:35:50+0000",
                "message": "直播祕技(0417第三版)\n- 機動防水直播台建置\n- 三種模式成果照\n- 簡報結尾加入吧！\n- BlackMagic mini Recorder",
                "id": "609179385825138"
            }
        ],
        "summary": {
            "total_count": 71
        }
    }
}