{
    "created_time": "2015-12-12T07:55:29+0000",
    "message": "在 Start-Up Hub 青創基地 的分享，以及後續討論的Hackpad\n--\nHackpad: https:\/\/dsp.hackpad.com\/L8FFA61oHcF",
    "story": "Pei-shen Wu shared a link to the group: g0v.tw 後勤中心.",
    "id": "387816094628136_899286376814436",
    "link": "http:\/\/www.slideshare.net\/peishenwu\/ss-56012640",
    "description": "有個構想，可以用Open data來挽救醫療崩壞，那就是「把健保審查核刪的資料公開」 大家都知道自己有交保費，也接受了醫療照顧，但你不知道的是健保真的有付錢嗎？ 我的想像是：做一個Dashboard，可以讓民眾去查，在某地區，做某手術或接受某治療，目前健保不付錢的比例有多高。 這個很重要， 我覺得民眾既然有付錢交保費…",
    "name": "健保核刪",
    "picture": "https:\/\/external.xx.fbcdn.net\/safe_image.php?d=AQBN4z-w13djfrNr&w=130&h=130&url=http%3A%2F%2Fcdn.slidesharecdn.com%2Fss_thumbnails%2F20151210-151210115840-thumbnail-4.jpg%3Fcb%3D1449749004&cfs=1&_nc_hash=AQAR4sSAPW3NUK2m",
    "updated_time": "2015-12-29T15:25:55+0000",
    "caption": "slideshare.net",
    "from": {
        "name": "Pei-shen Wu",
        "id": "1803031646396468"
    },
    "likes": {
        "summary": {
            "total_count": 46
        }
    },
    "comments": {
        "data": [
            {
                "created_time": "2015-12-12T08:21:25+0000",
                "from": {
                    "name": "Felice Wu",
                    "id": "2018440225097280"
                },
                "message": "所以說最終希望達到的成果是讓核刪標準變得透明-->民眾知道自己接受的醫療服務健保是否有給付--->沒有被給付的話會對健保局施壓，這樣嗎?",
                "id": "899295666813507"
            },
            {
                "created_time": "2015-12-12T08:22:12+0000",
                "from": {
                    "name": "Pei-shen Wu",
                    "id": "1803031646396468"
                },
                "message": "想法還需要iteration，不過概念上是這樣",
                "id": "899295830146824"
            },
            {
                "created_time": "2015-12-12T08:29:33+0000",
                "from": {
                    "name": "Felice Wu",
                    "id": "2018440225097280"
                },
                "message": "如果跟民眾說，我基於專業考量建議做A診療，但因為健保局刪這個刪很兇，所以我給你B就好，會增加他們向健保局施壓的誘因嗎?",
                "id": "899296963480044"
            },
            {
                "created_time": "2015-12-12T08:29:53+0000",
                "from": {
                    "name": "Felice Wu",
                    "id": "2018440225097280"
                },
                "message": "(怎麼都覺得然後大家就會罵醫院黑心...哀)",
                "id": "899297003480040"
            },
            {
                "created_time": "2015-12-20T05:58:24+0000",
                "from": {
                    "name": "Macpaul Lin",
                    "id": "10156042494092910"
                },
                "message": "https:\/\/youtu.be\/f6eaoYjsuXI",
                "id": "902984733111267"
            },
            {
                "created_time": "2015-12-20T05:58:31+0000",
                "from": {
                    "name": "Macpaul Lin",
                    "id": "10156042494092910"
                },
                "message": "https:\/\/youtu.be\/vEuj2tBE0NU",
                "id": "902984756444598"
            },
            {
                "created_time": "2015-12-20T15:02:37+0000",
                "from": {
                    "name": "Che Wei Liu",
                    "id": "10156142432594038"
                },
                "message": "哇賽被嚇到了還以為是今天大松...",
                "id": "903159099760497"
            },
            {
                "created_time": "2015-12-20T15:16:33+0000",
                "from": {
                    "name": "Macpaul Lin",
                    "id": "10156042494092910"
                },
                "message": "這是提案偷跑啊! 你應該要衝到中研院打卡的。 ＊誤超大＊",
                "id": "903164126426661"
            },
            {
                "created_time": "2015-12-20T15:40:43+0000",
                "from": {
                    "name": "Finjon Kiang",
                    "id": "10211662005529746"
                },
                "message": "轉轉轉：\nhttps:\/\/forum.doctorvoice.org\/viewtopic.php?f=1&t=111236\nhttps:\/\/www.facebook.com\/drugs.olc.tw\/posts\/475175489332041",
                "id": "903174339758973"
            },
            {
                "created_time": "2015-12-26T02:33:45+0000",
                "from": {
                    "name": "Macpaul Lin",
                    "id": "10156042494092910"
                },
                "message": "今天來了好多健保署的公務員喔 吳沛燊 沒來真可惜。下班後請記得找 Pei-Chi Lo",
                "id": "906474276095646"
            },
            {
                "created_time": "2015-12-27T01:52:37+0000",
                "from": {
                    "name": "Macpaul Lin",
                    "id": "10156042494092910"
                },
                "message": "https:\/\/www.youtube.com\/watch?v=bdTMHugYkOo",
                "id": "906963596046714"
            },
            {
                "created_time": "2015-12-27T01:53:00+0000",
                "from": {
                    "name": "Macpaul Lin",
                    "id": "10156042494092910"
                },
                "message": "https:\/\/www.youtube.com\/watch?v=Ea-YRf3lD3s",
                "id": "906963722713368"
            },
            {
                "created_time": "2015-12-27T02:11:25+0000",
                "from": {
                    "name": "Finjon Kiang",
                    "id": "10211662005529746"
                },
                "message": "所以換句話說，只要能夠有個方式讓健保一年省下 2% ，就可以不用被扭曲的核刪工作。\n\n把刪除金額當作 kpi 執行出現許多不合理的刪除案例",
                "id": "906968342712906"
            },
            {
                "created_time": "2015-12-27T05:16:32+0000",
                "from": {
                    "name": "Tom Shih",
                    "id": "10156061479633373"
                },
                "message": "所以健保局會主動公開過去每季每區核刪率嗎?\n所以健保局會主動公開過去每季每區核刪率嗎?\n所以健保局會主動公開過去每季每區核刪率嗎?\n \n我耳聞有家醫院某科一季被刪 20% \n不知道是不是八仙事件過後為了要讓財務支出減少, 又要滿足退補充保費的措施, 所以大刪特刪 ?\n\n#醫界不團結就是健保成功的秘訣",
                "id": "907012842708456"
            },
            {
                "created_time": "2015-12-27T09:45:11+0000",
                "from": {
                    "name": "Pei-Chi Lo",
                    "id": "10215091580704901"
                },
                "message": "同事的投影片釋出了喔~~cc0\nhttp:\/\/www.slideshare.net\/peichilo3\/g0v-po",
                "id": "907085442701196"
            },
            {
                "created_time": "2015-12-27T10:00:19+0000",
                "from": {
                    "name": "Pei-Chi Lo",
                    "id": "10215091580704901"
                },
                "message": "對不起綜合整理一下，以下這段也貼到hackpad上囉~\n　\n--\ng0v 17次大松沛燊有影片提案，當天剛好有衛福部的同事一起去：\n 　\n1. 提案後，快手同事在成果發表時幫補充了健保點值的背景資訊：說明影片 & 簡報釋出 (cc0)\nhttps:\/\/www.youtube.com\/watch?time_continue=15&v=bdTMHugYkOo\nhttp:\/\/www.slideshare.net\/peichilo3\/g0v-po\n　\n2. 另一個同事有提醒，做這個project的時候，可能要留意會來填報的可能大多會是比較極端的案例，比較正常範圍內的核刪不會在這個機制下呈現。但並不是說這個project不好，而是可能要做一個小提醒，讓觀看者理解，這個機制呈現的不是全貌，而有可能是比較極端的狀況。\n   　\n3. 從快手同事的簡報中，我自己的心得是：核刪就如同沛燊提到的，有許多負面的副作用，例如懲罰到好醫師等；除了想辦法讓核刪機制更(不要是懲罰好醫師)之外，也需要搭配思考：「如果核刪不是一個好機制，那怎麼樣可以解決浮濫申報的問題」。如果這個Project可以搭配著後面這個議題的思考，我個人覺得會是更完整的。\n　\n4. 具體例子像是，昨天大松同事報告後，ET Blue也做了回應\nhttps:\/\/www.youtube.com\/watch?v=Ea-YRf3lD3s\n提到浮濫申報的確存在，但目前的核刪會像地圖砲一樣無差別的懲罰其他好醫師，他建議應該要讓點值分配比例做區分，中重症的比例要更高，從根源杜絕浮濫申報的問題。-- 不論這個方法是不是正確的方向，我覺得如果這個Project也能搭配著這類型的思考，會對政策整體有更完整的討論。",
                "id": "907092372700503"
            },
            {
                "created_time": "2015-12-27T13:52:38+0000",
                "from": {
                    "name": "Tom Shih",
                    "id": "10156061479633373"
                },
                "message": "其實我覺得如果健保署直接公開沒有什麼不好, 甚至更可以達到控制醫療資源浪費的目的\n因為這個資料如果公開, 民眾可以選擇\n畢竟核刪率比較高的醫院, 事出必有因, 一定會再次思考這醫院發生什麼事",
                "id": "907168999359507"
            },
            {
                "created_time": "2015-12-28T03:51:25+0000",
                "from": {
                    "name": "Tom Shih",
                    "id": "10156061479633373"
                },
                "message": "也許試金石是 1\/18 之後  join 開放提案, 選完後\n看看還有沒有辦法找到夠多的人來連署\nhttp:\/\/join.gov.tw\/openup\/idea\/index",
                "id": "907447539331653"
            }
        ],
        "summary": {
            "total_count": 18
        }
    }
}