{
    "created_time": "2019-01-08T03:03:28+0000",
    "story": "Wu Min Hsuan shared a link to the group: g0v.tw 後勤中心.",
    "id": "387816094628136_1980123945397335",
    "link": "https:\/\/g0v.news\/2019%E5%85%A9%E5%A4%A7%E5%85%AC%E6%B0%91%E7%A7%91%E6%8A%80%E7%9B%9B%E6%9C%83%E7%8F%BE%E5%9C%A8%E9%96%8B%E6%94%BE%E6%8A%95%E7%A8%BF-e5d2691fdf04",
    "description": "截止日在 12月4日 跟 1月11日",
    "name": "2019兩大公民科技盛會現在開放投稿！ – g0v.news",
    "picture": "https:\/\/external.xx.fbcdn.net\/safe_image.php?w=130&h=130&url=https%3A%2F%2Fcdn-images-1.medium.com%2Fmax%2F1200%2F1%2Awv1xtq_6l3gXEsWVKUfdAw.jpeg&cfs=1&_nc_hash=AQAhqouZfFjPFybH",
    "updated_time": "2019-01-08T12:11:05+0000",
    "caption": "g0v.news",
    "likes": {
        "summary": {
            "total_count": 4
        }
    },
    "comments": {
        "data": [
            {
                "created_time": "2019-01-08T11:15:41+0000",
                "message": "剩下 TICTeC",
                "id": "1980552138687849"
            }
        ],
        "summary": {
            "total_count": 1
        }
    }
}