{
    "created_time": "2014-04-09T04:18:33+0000",
    "message": "報名開始了！第八次黑客松時間為 2014\/04\/19",
    "story": "Walkingice Chu shared a link to the group: g0v.tw 後勤中心.",
    "id": "387816094628136_605331729543237",
    "link": "http:\/\/g0v-tw.kktix.cc\/events\/g0v-hackath8n",
    "description": "☞ 為何要來 g0v.tw 每兩個月一回合黑客松，打造各式資訊透明化平台[1]，從資料透明開始，傳統\/新興、虛擬\/實體的公民參與繼續互相刺激交流，協作打造公民參與的新方法。 ☞ 來者何人 歡迎開...",
    "name": "g0v.tw hackath8n | 台灣零時政府第捌次解除戒嚴黑客松",
    "picture": "https:\/\/external.xx.fbcdn.net\/safe_image.php?d=AQD5DQtDzXEzjjCW&w=130&h=130&url=https%3A%2F%2Fassets0.kktix.com%2Fassets%2Fkktix-og-image-d78cd487cdb72fbf4b8b91185ff069bd.png&cfs=1&_nc_hash=AQDNAQgUjCSk8ySW",
    "updated_time": "2014-04-09T12:54:22+0000",
    "caption": "g0v-tw.kktix.cc",
    "from": {
        "name": "Walkingice Chu",
        "id": "10215366951548787"
    },
    "likes": {
        "summary": {
            "total_count": 64
        }
    },
    "comments": {
        "data": [
            {
                "created_time": "2014-04-09T06:48:12+0000",
                "from": {
                    "name": "鈕克力",
                    "id": "947477968789427"
                },
                "message": "這次黑客松的票開放一個半小時就沒了XDDD",
                "id": "605370429539367"
            },
            {
                "created_time": "2014-04-09T06:49:35+0000",
                "from": {
                    "name": "Jay Chen",
                    "id": "10156531093463676"
                },
                "message": "@@",
                "id": "605372509539159"
            },
            {
                "created_time": "2014-04-09T07:03:00+0000",
                "from": {
                    "name": "Wang Chih Wei",
                    "id": "10211778609960698"
                },
                "message": "太誇張啦！一次比一次難搶～",
                "id": "605404819535928"
            },
            {
                "created_time": "2014-04-09T07:12:54+0000",
                "from": {
                    "name": "Hong Tinda",
                    "id": "10215480788277885"
                },
                "message": "也太快了...",
                "id": "605419382867805"
            },
            {
                "created_time": "2014-04-09T07:19:32+0000",
                "from": {
                    "name": "Anthony Liu",
                    "id": "10157089581674992"
                },
                "message": "不管啦, 我要去佔領中研院",
                "id": "605420272867716"
            },
            {
                "created_time": "2014-04-09T07:40:22+0000",
                "from": {
                    "name": "Bo-Yuan Peng",
                    "id": "2123781540982196"
                },
                "message": "太誇張，我決定利用地主優勢佔領會議室 (誤)",
                "id": "605423476200729"
            },
            {
                "created_time": "2014-04-09T08:33:26+0000",
                "from": {
                    "name": "Finjon Kiang",
                    "id": "10211662005529746"
                },
                "message": "沒辦法上台北的也歡迎來這兒：\nhttp:\/\/finjonkiang.kktix.cc\/events\/g0v-hackath8n-tainan-nylon",
                "id": "605432149533195"
            },
            {
                "created_time": "2014-04-09T08:37:58+0000",
                "from": {
                    "name": "Jimy Huang",
                    "id": "10214071108564130"
                },
                "message": "據說有人要怒開路過團... XD",
                "id": "605433052866438"
            },
            {
                "created_time": "2014-04-09T08:43:54+0000",
                "from": {
                    "name": "Wang Chih Wei",
                    "id": "10211778609960698"
                },
                "message": "讓我買件軍綠大衣先～",
                "id": "605433806199696"
            },
            {
                "created_time": "2014-04-09T08:49:35+0000",
                "from": {
                    "name": "羅國甫",
                    "id": "2051594394856334"
                },
                "message": "沒跟上.....恨啊,我也要去占領中研院了,不然瞿大的提議也不錯啊",
                "id": "605435002866243"
            },
            {
                "created_time": "2014-04-09T08:57:33+0000",
                "from": {
                    "name": "D'whisky Tajfun",
                    "id": "1627662707269866"
                },
                "message": "路過中研院！",
                "id": "605436152866128"
            },
            {
                "created_time": "2014-04-09T09:20:50+0000",
                "from": {
                    "name": "Yiling Chen",
                    "id": "2033480690003058"
                },
                "message": "額滿了.....",
                "id": "605440796198997"
            },
            {
                "created_time": "2014-04-09T09:36:58+0000",
                "from": {
                    "name": "Mike  Lin",
                    "id": "2452493584974982"
                },
                "message": "看到就已經爆了...",
                "id": "605444349531975"
            },
            {
                "created_time": "2014-04-09T12:25:45+0000",
                "from": {
                    "name": "Anthony Liu",
                    "id": "10157089581674992"
                },
                "message": "Bo-Yuan Peng 你是要前一天晚上佔領主席台嗎?",
                "id": "605493549527055"
            },
            {
                "created_time": "2014-04-09T12:32:44+0000",
                "from": {
                    "name": "Anthony Liu",
                    "id": "10157089581674992"
                },
                "message": "沒跟到也可以路過",
                "id": "605495776193499"
            },
            {
                "created_time": "2014-04-09T12:44:02+0000",
                "from": {
                    "name": "唐鳳",
                    "id": "10156318975889928"
                },
                "message": "沒路過也可以遍地開花另開一場\nhttp:\/\/finjonkiang.kktix.cc\/events\/g0v-hackath8n-tainan-nylon",
                "id": "605498169526593"
            },
            {
                "created_time": "2014-04-09T12:46:05+0000",
                "from": {
                    "name": "Bert Wang",
                    "id": "861294890742239"
                },
                "message": "唐鳳 ++",
                "id": "605498589526551"
            },
            {
                "created_time": "2014-04-09T12:54:22+0000",
                "from": {
                    "name": "溫翊伶",
                    "id": "10155422937202252"
                },
                "message": "抗議啦，我也要跟彭柏源一起佔",
                "id": "605500562859687"
            }
        ],
        "summary": {
            "total_count": 18
        }
    }
}