{
    "created_time": "2019-04-12T08:41:40+0000",
    "message": "今年 Code for Japan Summit 在千葉縣，主題是「Spark Joy」XDDDDDDDD\n\n",
    "id": "387816094628136_2116927618383633",
    "link": "https:\/\/www.code4japan.org\/story\/code-for-japan-summit-2019-tickets\/",
    "description": "9月28日と29日に千葉で開催されるCode for Japan Summit 2019について3つの大事なお知らせです！ 1. 今年のテーマは「Spark Joy!（トキメキ）」 こんまり旋風がつい",
    "name": "Code for Japan Summit 2019（9\/28,29開催）のチケット発売開始！",
    "picture": "https:\/\/external.xx.fbcdn.net\/safe_image.php?d=AQAt4RB3jQrlJ8XJ&w=130&h=130&url=http%3A%2F%2Fwww.code4japan.org%2Fassets%2Fimages%2Fstory_dummy.png&cfs=1&_nc_hash=AQBKDyt4P_0H2uyb",
    "updated_time": "2019-04-12T14:56:38+0000",
    "caption": "code4japan.org",
    "likes": {
        "summary": {
            "total_count": 10
        }
    },
    "comments": {
        "data": [
            {
                "created_time": "2019-04-12T08:41:54+0000",
                "message": "",
                "id": "2116927811716947"
            },
            {
                "created_time": "2019-04-12T09:03:31+0000",
                "message": "Spark Joy！！！！",
                "id": "2116945365048525"
            },
            {
                "created_time": "2019-04-12T09:03:42+0000",
                "message": "",
                "id": "2116945451715183"
            },
            {
                "created_time": "2019-04-12T14:30:36+0000",
                "message": "All sessions have multiple language real-time caption by UDTalk app.",
                "id": "2117284375014624"
            }
        ],
        "summary": {
            "total_count": 4
        }
    }
}