{
    "created_time": "2019-05-03T05:07:25+0000",
    "message": "哈囉大家！我是 #大河小溪全民齊督工 專案的彥慈～\n來打個活動廣告，想請大家幫忙推給可能會有興趣的朋友們～謝謝！\n\n5\/18的《河川主題 Wiki Data 編輯聚》將會介紹專案「大河小溪全民齊督工」，並帶大家一起學習並操作如何在wiki data的資料庫中增加溪流的資料，希望你我能透過公民參與的力量推動台灣的河川資料數位化整理，為台灣的河川資料庫盡一份心力！\n\n我們需要各地河川社群的力量一起參與、協助補充台灣的河川相關資料，目前將會與wiki data合作，將其作為線上資料庫儲存社群們所彙編的資訊。期望關心同樣議題的您你妳，一起加入我們的行列！\n\n歡迎大家報名參加！",
    "id": "387816094628136_2148988278510900",
    "updated_time": "2019-05-03T07:54:36+0000",
    "likes": {
        "summary": {
            "total_count": 18
        }
    },
    "comments": {
        "data": [
            {
                "created_time": "2019-05-03T07:54:35+0000",
                "message": "推推",
                "id": "2149131515163243"
            }
        ],
        "summary": {
            "total_count": 1
        }
    }
}