{
    "created_time": "2019-04-02T14:36:50+0000",
    "message": "持續增加自主申報共議員：8位\n\n還是記得去年正副議長選舉後，一片譁然，更有人直呼「黑金政治已全面復辟」那你怎麼就放棄監督了呢？\n\n一、當「 正直與善良都回來了」成為最大公約數時，我們還能做什麼?\n\n要求議會全面轉播，包含政黨協商，再來是檢視財產申報，爬梳金流網路的第一步。\n\n但目前要檢視議員財產申報遇到最大障礙，就是「附帶條件」下的公開，議員們的財產申報，監察院規定不能翻拍、抄錄、錄影、攜出，並請針對同一申報人一年只能查閱一次，每次查閱至多30分鐘；財產申報法規定不用上網公開。\n\n所以我們決定要去監察院強制上架正副議長的財產申報，先從申報的各項總和開始，直轄市正副議長先行，希望拋磚引玉，喚起關注。\n\n因為我們堅信，權力必須透過相互制衡來確保不被過度濫用，議員們的財產申報不該落在灰色地帶。\n\n*感謝「文字記憶」高手加入，任務有機會付諸實行，現在我們不缺能力，缺的是「 勇氣」QQ\n\n*未來資料從監院帶出來後，會需要有人回到監院核對攜出資料，每人一年只能看某一位議員的資料申報一次（限30分鐘）\n\n二、先不論，為何？\n台北市長財產申報要上網公開，台北市議會議長不用\n高雄市長財產申報要上網公開，高雄市議會議長不用\n台中市長財產申報要上網公開，台中市議會議長不用\n⋯等等\n\n公眾若要有效的監督，必須建立在資訊的充分流通之下，最好的例子，就是當高雄議長帶頭反對市長至議會專案報告時，透過議事轉播，民眾可以一窺當下事實發生的經過，並進而給予評價，這就是透明之所以重要的原因。\n\n三、很重要，不顧他黨議員反對<<8位>>議員自主公開財產申報了！\n\n林亮君（台北市中山、大同）\n黃郁芬（台北市北投、士林）\n林穎孟（台北市大安、文山）\n林易瑩（台南市永康區）\n林于凱（高雄市三民區）\n黃捷（高雄市鳳山區）\n廖郁賢（雲林縣斗六、莿桐、林內）\n曾玟學（苗栗縣頭份、三灣、南庄）\n\n特別感謝蕭新晟 效率的架設網站，北市議會有科技長真好。",
    "id": "387816094628136_2102819839794411",
    "link": "https:\/\/open.npptw.org\/",
    "description": "依公職人員財產申報法第二條規定，各級民意代表都需依法申報財產，並依同法第六條二項上網公告，唯獨市議員從2008年開始只需申報不需公告，民眾想瞭解相關資訊只能親自到監察院申請調閱，看似管道暢通，不過魔鬼藏在.....",
    "name": "議員財產自主公開網",
    "picture": "https:\/\/external.xx.fbcdn.net\/safe_image.php?d=AQCizIrV20JSCLOb&w=130&h=130&url=https%3A%2F%2Fopen.npptw.org%2Fimages%2Fopenog.jpg&cfs=1&sx=48&sy=0&sw=605&sh=605&_nc_hash=AQBDh2zPRa5AKo_V",
    "updated_time": "2019-05-03T10:34:12+0000",
    "caption": "open.npptw.org",
    "shares": {
        "count": 18
    },
    "likes": {
        "summary": {
            "total_count": 114
        }
    },
    "comments": {
        "data": [
            {
                "created_time": "2019-04-02T14:42:29+0000",
                "message": "推勇氣",
                "id": "2102825733127155"
            },
            {
                "created_time": "2019-04-03T04:49:52+0000",
                "message": "411入監院",
                "id": "2103719689704426"
            },
            {
                "created_time": "2019-04-08T06:11:10+0000",
                "message": "以後就投時代就好了",
                "id": "2111057822303946"
            },
            {
                "created_time": "2019-04-11T11:34:46+0000",
                "message": "持續增加：曾玟學（苗栗縣頭份、三灣、南庄）",
                "id": "2115682175174844"
            },
            {
                "created_time": "2019-04-12T05:08:40+0000",
                "message": "哈囉～ 快速報告一下進度，昨天已經把高雄市許崑源議長的財申項目總合默背出來了，正在進行電子化。\n\n默背組：Kun-liang Lan  阿星",
                "id": "2116752741734454"
            },
            {
                "created_time": "2019-04-19T12:20:29+0000",
                "message": "「史萊姆的第一個家」還在更新？我們也是，6都議長默背過半（台南、高雄、台中、新北；桃園）",
                "id": "2127521980657530"
            },
            {
                "created_time": "2019-05-03T10:34:10+0000",
                "message": "六都議長副議長財產申報查閱，完成58%\n5\/8 顏市副議+桃園副議",
                "id": "2149275155148879"
            }
        ],
        "summary": {
            "total_count": 7
        }
    }
}