{
    "created_time": "2014-04-10T13:28:20+0000",
    "message": "這次 g0v 的直播影音存檔、逐字稿，所有協作紀錄以及程式，應該也典藏一份在中研院為「史料」。另外，「音地大帝」的影音紀錄，也都該典藏起來。 數位的，複製本來就較容易，但還需要即刻用文字紀錄時空背景（後設資料等）。我可以居中跟中研院相關人員聯繫。",
    "id": "387816094628136_605881202821623",
    "updated_time": "2014-04-10T16:08:57+0000",
    "from": {
        "name": "Tyng-Ruey Chuang",
        "id": "1758130377545063"
    },
    "likes": {
        "summary": {
            "total_count": 82
        }
    },
    "comments": {
        "data": [
            {
                "created_time": "2014-04-10T13:29:13+0000",
                "from": {
                    "name": "Chia-liang Kao",
                    "id": "10155373915470668"
                },
                "message": "就... 直接成為坑主了吧，不用居中了 XD",
                "id": "605881379488272"
            },
            {
                "created_time": "2014-04-10T13:30:20+0000",
                "from": {
                    "name": "Tyng-Ruey Chuang",
                    "id": "1758130377545063"
                },
                "message": "麻煩村長介紹 key persons 。 :-)",
                "id": "605881672821576"
            },
            {
                "created_time": "2014-04-10T13:30:58+0000",
                "from": {
                    "name": "Dongpo Deng",
                    "id": "10215101816163036"
                },
                "message": "沒有人!!",
                "id": "605881826154894"
            },
            {
                "created_time": "2014-04-10T13:31:21+0000",
                "from": {
                    "name": "Chia-liang Kao",
                    "id": "10155373915470668"
                },
                "message": "其實超展的開我都不認識了 XD 應該把需求跟 template 寫一下讓大家自己幫忙填就可以了？",
                "id": "605881909488219"
            },
            {
                "created_time": "2014-04-10T13:31:53+0000",
                "from": {
                    "name": "鄭智中",
                    "id": "10155459788420028"
                },
                "message": "就....翻一翻  fb 找中研院的人?",
                "id": "605882049488205"
            },
            {
                "created_time": "2014-04-10T13:34:06+0000",
                "from": {
                    "name": "Hsiao-wei Chiu",
                    "id": "10215521254163616"
                },
                "message": "是需要蒐集一下，現在散落在很多參與過直播人的各自帳號裡......",
                "id": "605882716154805"
            },
            {
                "created_time": "2014-04-10T13:34:47+0000",
                "from": {
                    "name": "Luoh Ren-Shan",
                    "id": "10213482055980337"
                },
                "message": "起一篇大家 fb 轉貼一下?",
                "id": "605882919488118"
            },
            {
                "created_time": "2014-04-10T13:35:09+0000",
                "from": {
                    "name": "Tyng-Ruey Chuang",
                    "id": "1758130377545063"
                },
                "message": "中研院已有人， Mindos Cheng 是否你當 g0v 窗口，我跟你接頭。",
                "id": "605883016154775"
            },
            {
                "created_time": "2014-04-10T13:39:10+0000",
                "from": {
                    "name": "Chia-liang Kao",
                    "id": "10155373915470668"
                },
                "message": "另外國圖也有人來信說希望能數位典藏 g0v.today... 不過全部都是 ajax... XD",
                "id": "605883946154682"
            },
            {
                "created_time": "2014-04-10T13:47:47+0000",
                "from": {
                    "name": "陳昱維",
                    "id": "1848118461866353"
                },
                "message": "開個hackpad統整？",
                "id": "605886606154416"
            },
            {
                "created_time": "2014-04-10T13:48:11+0000",
                "from": {
                    "name": "Monbaza Chang",
                    "id": "10155110645052750"
                },
                "message": "是「音地大帝」喔",
                "id": "605886716154405"
            },
            {
                "created_time": "2014-04-10T13:49:23+0000",
                "from": {
                    "name": "Tyng-Ruey Chuang",
                    "id": "1758130377545063"
                },
                "message": "我想目前我可以規劃一下影音檔案的部份。  g0v.today 上面是有 「影音紀錄」，不過這是傳到 youtube 上，轉碼過品質下降。我可以請 CC Taiwan 開一個 mailing list 來作人員聯繫，影音檔案可以放在一個 GNU MediaGoblin 的 instance 之上。",
                "id": "605887116154365"
            },
            {
                "created_time": "2014-04-10T13:50:23+0000",
                "from": {
                    "name": "鄭智中",
                    "id": "10155459788420028"
                },
                "message": "g0v 直播窗口很多啊。不過當然我可以幫忙。",
                "id": "605887692820974"
            },
            {
                "created_time": "2014-04-10T14:03:50+0000",
                "from": {
                    "name": "Tyng-Ruey Chuang",
                    "id": "1758130377545063"
                },
                "message": "Monbaza Taiwan Chang 謝！已更正。",
                "id": "605893462820397"
            },
            {
                "created_time": "2014-04-10T14:49:49+0000",
                "from": {
                    "name": "Wen-Chun Ni",
                    "id": "10217198797146392"
                },
                "message": "Tyng-Ruey Chuang 學長，那就認了吧！你那麼厲害，責無旁貸！",
                "id": "605908346152242"
            },
            {
                "created_time": "2014-04-10T14:52:23+0000",
                "from": {
                    "name": "Tyng-Ruey Chuang",
                    "id": "1758130377545063"
                },
                "message": "Wen-Chun Ni 我是路人甲啦！想不到果真網路上來相認！！",
                "id": "605909122818831"
            },
            {
                "created_time": "2014-04-10T14:53:26+0000",
                "from": {
                    "name": "Wen-Chun Ni",
                    "id": "10217198797146392"
                },
                "message": "學長，我們都是 38 號，你就為 38 之名認了。身為直屬學弟的我一定會一輩子崇拜你。 XD",
                "id": "605909359485474"
            },
            {
                "created_time": "2014-04-10T14:56:33+0000",
                "from": {
                    "name": "Tyng-Ruey Chuang",
                    "id": "1758130377545063"
                },
                "message": "後浪推前浪啦， g0v 裡學弟好多！",
                "id": "605910272818716"
            },
            {
                "created_time": "2014-04-10T14:58:07+0000",
                "from": {
                    "name": "Wen-Chun Ni",
                    "id": "10217198797146392"
                },
                "message": "對呀！最近我也有這種感覺。Chia-liang Kao 就讓我汗顏不已。",
                "id": "605910612818682"
            },
            {
                "created_time": "2014-04-10T16:08:57+0000",
                "from": {
                    "name": "Hsingyu Li",
                    "id": "1994967050516923"
                },
                "message": "我是存檔錄影的人，也是服貿專題網發起人，之後可以合作與交流。\n\n搜：服貿 專題網",
                "id": "605944372815306"
            }
        ],
        "summary": {
            "total_count": 20
        }
    }
}